[
  {
    "stat": "Ok",
    "time": "15-04-2026 09:15:00",
    "ssboe": "1776224700",
    "into": "13274.00",
    "inth": "13385.00",
    "intl": "13265.00",
    "intc": "13274.00",
    "intvwap": "13295.21",
    "intv": "32863",
    "intoi": "0",
    "v": "32863",
    "oi": "0"
  },
  {
    "stat": "Ok",
    "time": "15-04-2026 09:16:00",
    "ssboe": "1776224760",
    "into": "13272.00",
    "inth": "13283.00",
    "intl": "13237.00",
    "intc": "13276.00",
    "intvwap": "13260.39",
    "intv": "13060",
    "intoi": "0",
    "v": "45923",
    "oi": "0"
  },
  {
    "stat": "Ok",
    "time": "15-04-2026 09:17:00",
    "ssboe": "1776224820",
    "into": "13275.00",
    "inth": "13275.00",
    "intl": "13240.00",
    "intc": "13270.00",
    "intvwap": "13258.18",
    "intv": "7483",
    "intoi": "0",
    "v": "53406",
    "oi": "0"
  },
  {
    "stat": "Ok",
    "time": "15-04-2026 09:18:00",
    "ssboe": "1776224880",
    "into": "13267.00",
    "inth": "13278.00",
    "intl": "13265.00",
    "intc": "13268.00",
    "intvwap": "13273.04",
    "intv": "5650",
    "intoi": "0",
    "v": "59056",
    "oi": "0"
  },
  {
    "stat": "Ok",
    "time": "15-04-2026 09:19:00",
    "ssboe": "1776224940",
    "into": "13264.00",
    "inth": "13269.00",
    "intl": "13246.00",
    "intc": "13260.00",
    "intvwap": "13256.87",
    "intv": "6038",
    "intoi": "0",
    "v": "65094",
    "oi": "0"
  },
  {
    "stat": "Ok",
    "time": "15-04-2026 09:20:00",
    "ssboe": "1776225000",
    "into": "13255.00",
    "inth": "13270.00",
    "intl": "13247.00",
    "intc": "13270.00",
    "intvwap": "13254.89",
    "intv": "3734",
    "intoi": "0",
    "v": "68828",
    "oi": "0"
  },
  {
    "stat": "Ok",
    "time": "15-04-2026 09:21:00",
    "ssboe": "1776225060",
    "into": "13289.00",
    "inth": "13296.00",
    "intl": "13281.00",
    "intc": "13281.00",
    "intvwap": "13286.75",
    "intv": "5953",
    "intoi": "0",
    "v": "74781",
    "oi": "0"
  },
  {
    "stat": "Ok",
    "time": "15-04-2026 09:22:00",
    "ssboe": "1776225120",
    "into": "13278.00",
    "inth": "13282.00",
    "intl": "13260.00",
    "intc": "13264.00",
    "intvwap": "13271.53",
    "intv": "3659",
    "intoi": "0",
    "v": "78440",
    "oi": "0"
  },
  {
    "stat": "Ok",
    "time": "15-04-2026 09:23:00",
    "ssboe": "1776225180",
    "into": "13265.00",
    "inth": "13265.00",
    "intl": "13260.00",
    "intc": "13260.00",
    "intvwap": "13264.58",
    "intv": "3441",
    "intoi": "0",
    "v": "81881",
    "oi": "0"
  },
  {
    "stat": "Ok",
    "time": "15-04-2026 09:24:00",
    "ssboe": "1776225240",
    "into": "13255.00",
    "inth": "13258.00",
    "intl": "13250.00",
    "intc": "13250.00",
    "intvwap": "13255.17",
    "intv": "1714",
    "intoi": "0",
    "v": "83595",
    "oi": "0"
  },
  {
    "stat": "Ok",
    "time": "15-04-2026 09:25:00",
    "ssboe": "1776225300",
    "into": "13251.00",
    "inth": "13267.00",
    "intl": "13250.00",
    "intc": "13266.00",
    "intvwap": "13256.97",
    "intv": "3816",
    "intoi": "0",
    "v": "87411",
    "oi": "0"
  },
  {
    "stat": "Ok",
    "time": "15-04-2026 09:26:00",
    "ssboe": "1776225360",
    "into": "13267.00",
    "inth": "13271.00",
    "intl": "13254.00",
    "intc": "13254.00",
    "intvwap": "13265.97",
    "intv": "3898",
    "intoi": "0",
    "v": "91309",
    "oi": "0"
  },
  {
    "stat": "Ok",
    "time": "15-04-2026 09:27:00",
    "ssboe": "1776225420",
    "into": "13256.00",
    "inth": "13256.00",
    "intl": "13240.00",
    "intc": "13240.00",
    "intvwap": "13246.87",
    "intv": "3525",
    "intoi": "0",
    "v": "94834",
    "oi": "0"
  },
  {
    "stat": "Ok",
    "time": "15-04-2026 09:28:00",
    "ssboe": "1776225480",
    "into": "13233.00",
    "inth": "13251.00",
    "intl": "13231.00",
    "intc": "13245.00",
    "intvwap": "13239.86",
    "intv": "2427",
    "intoi": "0",
    "v": "97261",
    "oi": "0"
  },
  {
    "stat": "Ok",
    "time": "15-04-2026 09:29:00",
    "ssboe": "1776225540",
    "into": "13247.00",
    "inth": "13247.00",
    "intl": "13236.00",
    "intc": "13236.00",
    "intvwap": "13242.38",
    "intv": "1268",
    "intoi": "0",
    "v": "98529",
    "oi": "0"
  },
  {
    "stat": "Ok",
    "time": "15-04-2026 09:30:00",
    "ssboe": "1776225600",
    "into": "13232.00",
    "inth": "13234.00",
    "intl": "13221.00",
    "intc": "13229.00",
    "intvwap": "13230.24",
    "intv": "2670",
    "intoi": "0",
    "v": "101199",
    "oi": "0"
  },
  {
    "stat": "Ok",
    "time": "15-04-2026 09:31:00",
    "ssboe": "1776225660",
    "into": "13226.00",
    "inth": "13227.00",
    "intl": "13212.00",
    "intc": "13223.00",
    "intvwap": "13221.54",
    "intv": "2532",
    "intoi": "0",
    "v": "103731",
    "oi": "0"
  },
  {
    "stat": "Ok",
    "time": "15-04-2026 09:32:00",
    "ssboe": "1776225720",
    "into": "13225.00",
    "inth": "13228.00",
    "intl": "13219.00",
    "intc": "13226.00",
    "intvwap": "13224.01",
    "intv": "2085",
    "intoi": "0",
    "v": "105816",
    "oi": "0"
  },
  {
    "stat": "Ok",
    "time": "15-04-2026 09:33:00",
    "ssboe": "1776225780",
    "into": "13225.00",
    "inth": "13226.00",
    "intl": "13221.00",
    "intc": "13221.00",
    "intvwap": "13223.48",
    "intv": "1436",
    "intoi": "0",
    "v": "107252",
    "oi": "0"
  },
  {
    "stat": "Ok",
    "time": "15-04-2026 09:34:00",
    "ssboe": "1776225840",
    "into": "13220.00",
    "inth": "13220.00",
    "intl": "13200.00",
    "intc": "13201.00",
    "intvwap": "13210.99",
    "intv": "2761",
    "intoi": "0",
    "v": "110013",
    "oi": "0"
  },
  {
    "stat": "Ok",
    "time": "15-04-2026 09:35:00",
    "ssboe": "1776225900",
    "into": "13209.00",
    "inth": "13216.00",
    "intl": "13209.00",
    "intc": "13212.00",
    "intvwap": "13209.00",
    "intv": "2879",
    "intoi": "0",
    "v": "112892",
    "oi": "0"
  },
  {
    "stat": "Ok",
    "time": "15-04-2026 09:36:00",
    "ssboe": "1776225960",
    "into": "13217.00",
    "inth": "13227.00",
    "intl": "13215.00",
    "intc": "13227.00",
    "intvwap": "13217.87",
    "intv": "1975",
    "intoi": "0",
    "v": "114867",
    "oi": "0"
  },
  {
    "stat": "Ok",
    "time": "15-04-2026 09:37:00",
    "ssboe": "1776226020",
    "into": "13225.00",
    "inth": "13227.00",
    "intl": "13205.00",
    "intc": "13214.00",
    "intvwap": "13221.47",
    "intv": "2026",
    "intoi": "0",
    "v": "116893",
    "oi": "0"
  },
  {
    "stat": "Ok",
    "time": "15-04-2026 09:38:00",
    "ssboe": "1776226080",
    "into": "13217.00",
    "inth": "13227.00",
    "intl": "13211.00",
    "intc": "13215.00",
    "intvwap": "13219.43",
    "intv": "1204",
    "intoi": "0",
    "v": "118097",
    "oi": "0"
  },
  {
    "stat": "Ok",
    "time": "15-04-2026 09:39:00",
    "ssboe": "1776226140",
    "into": "13206.00",
    "inth": "13218.00",
    "intl": "13206.00",
    "intc": "13218.00",
    "intvwap": "13210.57",
    "intv": "2134",
    "intoi": "0",
    "v": "120231",
    "oi": "0"
  },
  {
    "stat": "Ok",
    "time": "15-04-2026 09:40:00",
    "ssboe": "1776226200",
    "into": "13222.00",
    "inth": "13242.00",
    "intl": "13221.00",
    "intc": "13242.00",
    "intvwap": "13228.49",
    "intv": "1760",
    "intoi": "0",
    "v": "121991",
    "oi": "0"
  },
  {
    "stat": "Ok",
    "time": "15-04-2026 09:41:00",
    "ssboe": "1776226260",
    "into": "13239.00",
    "inth": "13243.00",
    "intl": "13239.00",
    "intc": "13243.00",
    "intvwap": "13241.91",
    "intv": "1248",
    "intoi": "0",
    "v": "123239",
    "oi": "0"
  },
  {
    "stat": "Ok",
    "time": "15-04-2026 09:42:00",
    "ssboe": "1776226320",
    "into": "13242.00",
    "inth": "13264.00",
    "intl": "13242.00",
    "intc": "13264.00",
    "intvwap": "13248.06",
    "intv": "2716",
    "intoi": "0",
    "v": "125955",
    "oi": "0"
  },
  {
    "stat": "Ok",
    "time": "15-04-2026 09:43:00",
    "ssboe": "1776226380",
    "into": "13267.00",
    "inth": "13299.00",
    "intl": "13264.00",
    "intc": "13296.00",
    "intvwap": "13275.52",
    "intv": "6737",
    "intoi": "0",
    "v": "132692",
    "oi": "0"
  },
  {
    "stat": "Ok",
    "time": "15-04-2026 09:44:00",
    "ssboe": "1776226440",
    "into": "13309.00",
    "inth": "13330.00",
    "intl": "13309.00",
    "intc": "13320.00",
    "intvwap": "13312.33",
    "intv": "18049",
    "intoi": "0",
    "v": "150741",
    "oi": "0"
  },
  {
    "stat": "Ok",
    "time": "15-04-2026 09:45:00",
    "ssboe": "1776226500",
    "into": "13314.00",
    "inth": "13328.00",
    "intl": "13314.00",
    "intc": "13326.00",
    "intvwap": "13321.47",
    "intv": "3750",
    "intoi": "0",
    "v": "154491",
    "oi": "0"
  },
  {
    "stat": "Ok",
    "time": "15-04-2026 09:46:00",
    "ssboe": "1776226560",
    "into": "13324.00",
    "inth": "13340.00",
    "intl": "13324.00",
    "intc": "13330.00",
    "intvwap": "13331.47",
    "intv": "4982",
    "intoi": "0",
    "v": "159473",
    "oi": "0"
  },
  {
    "stat": "Ok",
    "time": "15-04-2026 09:47:00",
    "ssboe": "1776226620",
    "into": "13329.00",
    "inth": "13340.00",
    "intl": "13322.00",
    "intc": "13326.00",
    "intvwap": "13334.73",
    "intv": "3054",
    "intoi": "0",
    "v": "162527",
    "oi": "0"
  },
  {
    "stat": "Ok",
    "time": "15-04-2026 09:48:00",
    "ssboe": "1776226680",
    "into": "13322.00",
    "inth": "13322.00",
    "intl": "13272.00",
    "intc": "13277.00",
    "intvwap": "13289.62",
    "intv": "4141",
    "intoi": "0",
    "v": "166668",
    "oi": "0"
  },
  {
    "stat": "Ok",
    "time": "15-04-2026 09:49:00",
    "ssboe": "1776226740",
    "into": "13282.00",
    "inth": "13293.00",
    "intl": "13274.00",
    "intc": "13286.00",
    "intvwap": "13283.83",
    "intv": "1634",
    "intoi": "0",
    "v": "168302",
    "oi": "0"
  },
  {
    "stat": "Ok",
    "time": "15-04-2026 09:50:00",
    "ssboe": "1776226800",
    "into": "13287.00",
    "inth": "13289.00",
    "intl": "13261.00",
    "intc": "13266.00",
    "intvwap": "13269.09",
    "intv": "2255",
    "intoi": "0",
    "v": "170557",
    "oi": "0"
  },
  {
    "stat": "Ok",
    "time": "15-04-2026 09:51:00",
    "ssboe": "1776226860",
    "into": "13265.00",
    "inth": "13273.00",
    "intl": "13265.00",
    "intc": "13272.00",
    "intvwap": "13267.17",
    "intv": "2436",
    "intoi": "0",
    "v": "172993",
    "oi": "0"
  },
  {
    "stat": "Ok",
    "time": "15-04-2026 09:52:00",
    "ssboe": "1776226920",
    "into": "13270.00",
    "inth": "13297.00",
    "intl": "13270.00",
    "intc": "13296.00",
    "intvwap": "13285.08",
    "intv": "1960",
    "intoi": "0",
    "v": "174953",
    "oi": "0"
  },
  {
    "stat": "Ok",
    "time": "15-04-2026 09:53:00",
    "ssboe": "1776226980",
    "into": "13305.00",
    "inth": "13307.00",
    "intl": "13298.00",
    "intc": "13304.00",
    "intvwap": "13301.75",
    "intv": "2267",
    "intoi": "0",
    "v": "177220",
    "oi": "0"
  },
  {
    "stat": "Ok",
    "time": "15-04-2026 09:54:00",
    "ssboe": "1776227040",
    "into": "13301.00",
    "inth": "13319.00",
    "intl": "13297.00",
    "intc": "13317.00",
    "intvwap": "13305.97",
    "intv": "2527",
    "intoi": "0",
    "v": "179747",
    "oi": "0"
  },
  {
    "stat": "Ok",
    "time": "15-04-2026 09:55:00",
    "ssboe": "1776227100",
    "into": "13310.00",
    "inth": "13330.00",
    "intl": "13310.00",
    "intc": "13317.00",
    "intvwap": "13319.20",
    "intv": "2482",
    "intoi": "0",
    "v": "182229",
    "oi": "0"
  },
  {
    "stat": "Ok",
    "time": "15-04-2026 09:56:00",
    "ssboe": "1776227160",
    "into": "13319.00",
    "inth": "13319.00",
    "intl": "13304.00",
    "intc": "13315.00",
    "intvwap": "13311.15",
    "intv": "1321",
    "intoi": "0",
    "v": "183550",
    "oi": "0"
  },
  {
    "stat": "Ok",
    "time": "15-04-2026 09:57:00",
    "ssboe": "1776227220",
    "into": "13318.00",
    "inth": "13330.00",
    "intl": "13314.00",
    "intc": "13329.00",
    "intvwap": "13320.96",
    "intv": "2526",
    "intoi": "0",
    "v": "186076",
    "oi": "0"
  },
  {
    "stat": "Ok",
    "time": "15-04-2026 09:58:00",
    "ssboe": "1776227280",
    "into": "13328.00",
    "inth": "13338.00",
    "intl": "13326.00",
    "intc": "13329.00",
    "intvwap": "13332.83",
    "intv": "1649",
    "intoi": "0",
    "v": "187725",
    "oi": "0"
  },
  {
    "stat": "Ok",
    "time": "15-04-2026 09:59:00",
    "ssboe": "1776227340",
    "into": "13325.00",
    "inth": "13327.00",
    "intl": "13321.00",
    "intc": "13324.00",
    "intvwap": "13324.13",
    "intv": "1307",
    "intoi": "0",
    "v": "189032",
    "oi": "0"
  },
  {
    "stat": "Ok",
    "time": "15-04-2026 10:00:00",
    "ssboe": "1776227400",
    "into": "13327.00",
    "inth": "13336.00",
    "intl": "13318.00",
    "intc": "13336.00",
    "intvwap": "13328.32",
    "intv": "2525",
    "intoi": "0",
    "v": "191557",
    "oi": "0"
  },
  {
    "stat": "Ok",
    "time": "15-04-2026 10:01:00",
    "ssboe": "1776227460",
    "into": "13334.00",
    "inth": "13344.00",
    "intl": "13330.00",
    "intc": "13333.00",
    "intvwap": "13337.12",
    "intv": "2174",
    "intoi": "0",
    "v": "193731",
    "oi": "0"
  },
  {
    "stat": "Ok",
    "time": "15-04-2026 10:02:00",
    "ssboe": "1776227520",
    "into": "13332.00",
    "inth": "13352.00",
    "intl": "13332.00",
    "intc": "13343.00",
    "intvwap": "13345.85",
    "intv": "8474",
    "intoi": "0",
    "v": "202205",
    "oi": "0"
  },
  {
    "stat": "Ok",
    "time": "15-04-2026 10:03:00",
    "ssboe": "1776227580",
    "into": "13341.00",
    "inth": "13346.00",
    "intl": "13337.00",
    "intc": "13341.00",
    "intvwap": "13342.43",
    "intv": "1257",
    "intoi": "0",
    "v": "203462",
    "oi": "0"
  },
  {
    "stat": "Ok",
    "time": "15-04-2026 10:04:00",
    "ssboe": "1776227640",
    "into": "13345.00",
    "inth": "13351.00",
    "intl": "13340.00",
    "intc": "13345.00",
    "intvwap": "13344.77",
    "intv": "1518",
    "intoi": "0",
    "v": "204980",
    "oi": "0"
  },
  {
    "stat": "Ok",
    "time": "15-04-2026 10:05:00",
    "ssboe": "1776227700",
    "into": "13346.00",
    "inth": "13354.00",
    "intl": "13342.00",
    "intc": "13348.00",
    "intvwap": "13348.83",
    "intv": "2475",
    "intoi": "0",
    "v": "207455",
    "oi": "0"
  },
  {
    "stat": "Ok",
    "time": "15-04-2026 10:06:00",
    "ssboe": "1776227760",
    "into": "13346.00",
    "inth": "13351.00",
    "intl": "13339.00",
    "intc": "13341.00",
    "intvwap": "13346.10",
    "intv": "1978",
    "intoi": "0",
    "v": "209433",
    "oi": "0"
  },
  {
    "stat": "Ok",
    "time": "15-04-2026 10:07:00",
    "ssboe": "1776227820",
    "into": "13339.00",
    "inth": "13350.00",
    "intl": "13336.00",
    "intc": "13347.00",
    "intvwap": "13346.71",
    "intv": "1494",
    "intoi": "0",
    "v": "210927",
    "oi": "0"
  },
  {
    "stat": "Ok",
    "time": "15-04-2026 10:08:00",
    "ssboe": "1776227880",
    "into": "13345.00",
    "inth": "13348.00",
    "intl": "13335.00",
    "intc": "13340.00",
    "intvwap": "13344.67",
    "intv": "937",
    "intoi": "0",
    "v": "211864",
    "oi": "0"
  },
  {
    "stat": "Ok",
    "time": "15-04-2026 10:09:00",
    "ssboe": "1776227940",
    "into": "13336.00",
    "inth": "13352.00",
    "intl": "13333.00",
    "intc": "13349.00",
    "intvwap": "13342.39",
    "intv": "1716",
    "intoi": "0",
    "v": "213580",
    "oi": "0"
  },
  {
    "stat": "Ok",
    "time": "15-04-2026 10:10:00",
    "ssboe": "1776228000",
    "into": "13350.00",
    "inth": "13350.00",
    "intl": "13333.00",
    "intc": "13340.00",
    "intvwap": "13339.34",
    "intv": "3555",
    "intoi": "0",
    "v": "217135",
    "oi": "0"
  },
  {
    "stat": "Ok",
    "time": "15-04-2026 10:11:00",
    "ssboe": "1776228060",
    "into": "13338.00",
    "inth": "13338.00",
    "intl": "13312.00",
    "intc": "13322.00",
    "intvwap": "13320.65",
    "intv": "2734",
    "intoi": "0",
    "v": "219869",
    "oi": "0"
  },
  {
    "stat": "Ok",
    "time": "15-04-2026 10:12:00",
    "ssboe": "1776228120",
    "into": "13320.00",
    "inth": "13329.00",
    "intl": "13320.00",
    "intc": "13329.00",
    "intvwap": "13326.35",
    "intv": "1142",
    "intoi": "0",
    "v": "221011",
    "oi": "0"
  },
  {
    "stat": "Ok",
    "time": "15-04-2026 10:13:00",
    "ssboe": "1776228180",
    "into": "13327.00",
    "inth": "13335.00",
    "intl": "13327.00",
    "intc": "13334.00",
    "intvwap": "13330.48",
    "intv": "1498",
    "intoi": "0",
    "v": "222509",
    "oi": "0"
  },
  {
    "stat": "Ok",
    "time": "15-04-2026 10:14:00",
    "ssboe": "1776228240",
    "into": "13336.00",
    "inth": "13342.00",
    "intl": "13335.00",
    "intc": "13342.00",
    "intvwap": "13339.84",
    "intv": "1084",
    "intoi": "0",
    "v": "223593",
    "oi": "0"
  },
  {
    "stat": "Ok",
    "time": "15-04-2026 10:15:00",
    "ssboe": "1776228300",
    "into": "13341.00",
    "inth": "13353.00",
    "intl": "13341.00",
    "intc": "13349.00",
    "intvwap": "13348.47",
    "intv": "1708",
    "intoi": "0",
    "v": "225301",
    "oi": "0"
  },
  {
    "stat": "Ok",
    "time": "15-04-2026 10:16:00",
    "ssboe": "1776228360",
    "into": "13347.00",
    "inth": "13355.00",
    "intl": "13345.00",
    "intc": "13348.00",
    "intvwap": "13351.31",
    "intv": "2013",
    "intoi": "0",
    "v": "227314",
    "oi": "0"
  },
  {
    "stat": "Ok",
    "time": "15-04-2026 10:17:00",
    "ssboe": "1776228420",
    "into": "13344.00",
    "inth": "13346.00",
    "intl": "13341.00",
    "intc": "13345.00",
    "intvwap": "13344.62",
    "intv": "839",
    "intoi": "0",
    "v": "228153",
    "oi": "0"
  },
  {
    "stat": "Ok",
    "time": "15-04-2026 10:18:00",
    "ssboe": "1776228480",
    "into": "13344.00",
    "inth": "13354.00",
    "intl": "13344.00",
    "intc": "13350.00",
    "intvwap": "13348.26",
    "intv": "2284",
    "intoi": "0",
    "v": "230437",
    "oi": "0"
  },
  {
    "stat": "Ok",
    "time": "15-04-2026 10:19:00",
    "ssboe": "1776228540",
    "into": "13346.00",
    "inth": "13378.00",
    "intl": "13346.00",
    "intc": "13371.00",
    "intvwap": "13363.82",
    "intv": "5149",
    "intoi": "0",
    "v": "235586",
    "oi": "0"
  },
  {
    "stat": "Ok",
    "time": "15-04-2026 10:20:00",
    "ssboe": "1776228600",
    "into": "13365.00",
    "inth": "13389.00",
    "intl": "13365.00",
    "intc": "13388.00",
    "intvwap": "13380.85",
    "intv": "5220",
    "intoi": "0",
    "v": "240806",
    "oi": "0"
  },
  {
    "stat": "Ok",
    "time": "15-04-2026 10:21:00",
    "ssboe": "1776228660",
    "into": "13385.00",
    "inth": "13385.00",
    "intl": "13368.00",
    "intc": "13375.00",
    "intvwap": "13375.57",
    "intv": "1332",
    "intoi": "0",
    "v": "242138",
    "oi": "0"
  },
  {
    "stat": "Ok",
    "time": "15-04-2026 10:22:00",
    "ssboe": "1776228720",
    "into": "13374.00",
    "inth": "13383.00",
    "intl": "13371.00",
    "intc": "13382.00",
    "intvwap": "13377.03",
    "intv": "1729",
    "intoi": "0",
    "v": "243867",
    "oi": "0"
  },
  {
    "stat": "Ok",
    "time": "15-04-2026 10:23:00",
    "ssboe": "1776228780",
    "into": "13381.00",
    "inth": "13399.00",
    "intl": "13380.00",
    "intc": "13392.00",
    "intvwap": "13390.21",
    "intv": "2971",
    "intoi": "0",
    "v": "246838",
    "oi": "0"
  },
  {
    "stat": "Ok",
    "time": "15-04-2026 10:24:00",
    "ssboe": "1776228840",
    "into": "13390.00",
    "inth": "13411.00",
    "intl": "13386.00",
    "intc": "13409.00",
    "intvwap": "13398.19",
    "intv": "6079",
    "intoi": "0",
    "v": "252917",
    "oi": "0"
  },
  {
    "stat": "Ok",
    "time": "15-04-2026 10:25:00",
    "ssboe": "1776228900",
    "into": "13410.00",
    "inth": "13418.00",
    "intl": "13407.00",
    "intc": "13411.00",
    "intvwap": "13415.05",
    "intv": "1916",
    "intoi": "0",
    "v": "254833",
    "oi": "0"
  },
  {
    "stat": "Ok",
    "time": "15-04-2026 10:26:00",
    "ssboe": "1776228960",
    "into": "13413.00",
    "inth": "13422.00",
    "intl": "13410.00",
    "intc": "13419.00",
    "intvwap": "13417.05",
    "intv": "3196",
    "intoi": "0",
    "v": "258029",
    "oi": "0"
  },
  {
    "stat": "Ok",
    "time": "15-04-2026 10:27:00",
    "ssboe": "1776229020",
    "into": "13416.00",
    "inth": "13430.00",
    "intl": "13416.00",
    "intc": "13425.00",
    "intvwap": "13424.04",
    "intv": "2333",
    "intoi": "0",
    "v": "260362",
    "oi": "0"
  },
  {
    "stat": "Ok",
    "time": "15-04-2026 10:28:00",
    "ssboe": "1776229080",
    "into": "13424.00",
    "inth": "13431.00",
    "intl": "13422.00",
    "intc": "13426.00",
    "intvwap": "13428.06",
    "intv": "1474",
    "intoi": "0",
    "v": "261836",
    "oi": "0"
  },
  {
    "stat": "Ok",
    "time": "15-04-2026 10:29:00",
    "ssboe": "1776229140",
    "into": "13424.00",
    "inth": "13432.00",
    "intl": "13422.00",
    "intc": "13427.00",
    "intvwap": "13427.12",
    "intv": "1460",
    "intoi": "0",
    "v": "263296",
    "oi": "0"
  },
  {
    "stat": "Ok",
    "time": "15-04-2026 10:30:00",
    "ssboe": "1776229200",
    "into": "13425.00",
    "inth": "13444.00",
    "intl": "13425.00",
    "intc": "13430.00",
    "intvwap": "13435.98",
    "intv": "3313",
    "intoi": "0",
    "v": "266609",
    "oi": "0"
  },
  {
    "stat": "Ok",
    "time": "15-04-2026 10:31:00",
    "ssboe": "1776229260",
    "into": "13426.00",
    "inth": "13435.00",
    "intl": "13412.00",
    "intc": "13412.00",
    "intvwap": "13425.01",
    "intv": "2855",
    "intoi": "0",
    "v": "269464",
    "oi": "0"
  },
  {
    "stat": "Ok",
    "time": "15-04-2026 10:32:00",
    "ssboe": "1776229320",
    "into": "13414.00",
    "inth": "13422.00",
    "intl": "13406.00",
    "intc": "13419.00",
    "intvwap": "13416.11",
    "intv": "4045",
    "intoi": "0",
    "v": "273509",
    "oi": "0"
  },
  {
    "stat": "Ok",
    "time": "15-04-2026 10:33:00",
    "ssboe": "1776229380",
    "into": "13418.00",
    "inth": "13436.00",
    "intl": "13417.00",
    "intc": "13433.00",
    "intvwap": "13423.76",
    "intv": "1356",
    "intoi": "0",
    "v": "274865",
    "oi": "0"
  },
  {
    "stat": "Ok",
    "time": "15-04-2026 10:34:00",
    "ssboe": "1776229440",
    "into": "13434.00",
    "inth": "13437.00",
    "intl": "13427.00",
    "intc": "13429.00",
    "intvwap": "13432.57",
    "intv": "1163",
    "intoi": "0",
    "v": "276028",
    "oi": "0"
  },
  {
    "stat": "Ok",
    "time": "15-04-2026 10:35:00",
    "ssboe": "1776229500",
    "into": "13433.00",
    "inth": "13440.00",
    "intl": "13429.00",
    "intc": "13434.00",
    "intvwap": "13436.22",
    "intv": "1572",
    "intoi": "0",
    "v": "277600",
    "oi": "0"
  },
  {
    "stat": "Ok",
    "time": "15-04-2026 10:36:00",
    "ssboe": "1776229560",
    "into": "13435.00",
    "inth": "13440.00",
    "intl": "13434.00",
    "intc": "13437.00",
    "intvwap": "13436.13",
    "intv": "935",
    "intoi": "0",
    "v": "278535",
    "oi": "0"
  },
  {
    "stat": "Ok",
    "time": "15-04-2026 10:37:00",
    "ssboe": "1776229620",
    "into": "13433.00",
    "inth": "13435.00",
    "intl": "13428.00",
    "intc": "13434.00",
    "intvwap": "13432.58",
    "intv": "878",
    "intoi": "0",
    "v": "279413",
    "oi": "0"
  },
  {
    "stat": "Ok",
    "time": "15-04-2026 10:38:00",
    "ssboe": "1776229680",
    "into": "13432.00",
    "inth": "13442.00",
    "intl": "13431.00",
    "intc": "13439.00",
    "intvwap": "13438.80",
    "intv": "2670",
    "intoi": "0",
    "v": "282083",
    "oi": "0"
  },
  {
    "stat": "Ok",
    "time": "15-04-2026 10:39:00",
    "ssboe": "1776229740",
    "into": "13436.00",
    "inth": "13438.00",
    "intl": "13421.00",
    "intc": "13424.00",
    "intvwap": "13426.91",
    "intv": "1945",
    "intoi": "0",
    "v": "284028",
    "oi": "0"
  },
  {
    "stat": "Ok",
    "time": "15-04-2026 10:40:00",
    "ssboe": "1776229800",
    "into": "13422.00",
    "inth": "13436.00",
    "intl": "13420.00",
    "intc": "13435.00",
    "intvwap": "13429.64",
    "intv": "1539",
    "intoi": "0",
    "v": "285567",
    "oi": "0"
  },
  {
    "stat": "Ok",
    "time": "15-04-2026 10:41:00",
    "ssboe": "1776229860",
    "into": "13436.00",
    "inth": "13447.00",
    "intl": "13433.00",
    "intc": "13447.00",
    "intvwap": "13441.97",
    "intv": "1873",
    "intoi": "0",
    "v": "287440",
    "oi": "0"
  },
  {
    "stat": "Ok",
    "time": "15-04-2026 10:42:00",
    "ssboe": "1776229920",
    "into": "13446.00",
    "inth": "13458.00",
    "intl": "13443.00",
    "intc": "13457.00",
    "intvwap": "13451.48",
    "intv": "3747",
    "intoi": "0",
    "v": "291187",
    "oi": "0"
  },
  {
    "stat": "Ok",
    "time": "15-04-2026 10:43:00",
    "ssboe": "1776229980",
    "into": "13456.00",
    "inth": "13463.00",
    "intl": "13456.00",
    "intc": "13460.00",
    "intvwap": "13458.80",
    "intv": "2252",
    "intoi": "0",
    "v": "293439",
    "oi": "0"
  },
  {
    "stat": "Ok",
    "time": "15-04-2026 10:44:00",
    "ssboe": "1776230040",
    "into": "13459.00",
    "inth": "13461.00",
    "intl": "13456.00",
    "intc": "13460.00",
    "intvwap": "13458.42",
    "intv": "946",
    "intoi": "0",
    "v": "294385",
    "oi": "0"
  },
  {
    "stat": "Ok",
    "time": "15-04-2026 10:45:00",
    "ssboe": "1776230100",
    "into": "13459.00",
    "inth": "13463.00",
    "intl": "13455.00",
    "intc": "13458.00",
    "intvwap": "13459.82",
    "intv": "1561",
    "intoi": "0",
    "v": "295946",
    "oi": "0"
  },
  {
    "stat": "Ok",
    "time": "15-04-2026 10:46:00",
    "ssboe": "1776230160",
    "into": "13453.00",
    "inth": "13456.00",
    "intl": "13443.00",
    "intc": "13449.00",
    "intvwap": "13449.40",
    "intv": "1567",
    "intoi": "0",
    "v": "297513",
    "oi": "0"
  },
  {
    "stat": "Ok",
    "time": "15-04-2026 10:47:00",
    "ssboe": "1776230220",
    "into": "13450.00",
    "inth": "13464.00",
    "intl": "13446.00",
    "intc": "13461.00",
    "intvwap": "13457.59",
    "intv": "1448",
    "intoi": "0",
    "v": "298961",
    "oi": "0"
  },
  {
    "stat": "Ok",
    "time": "15-04-2026 10:48:00",
    "ssboe": "1776230280",
    "into": "13463.00",
    "inth": "13468.00",
    "intl": "13459.00",
    "intc": "13466.00",
    "intvwap": "13463.44",
    "intv": "2339",
    "intoi": "0",
    "v": "301300",
    "oi": "0"
  },
  {
    "stat": "Ok",
    "time": "15-04-2026 10:49:00",
    "ssboe": "1776230340",
    "into": "13465.00",
    "inth": "13470.00",
    "intl": "13461.00",
    "intc": "13470.00",
    "intvwap": "13464.63",
    "intv": "1518",
    "intoi": "0",
    "v": "302818",
    "oi": "0"
  },
  {
    "stat": "Ok",
    "time": "15-04-2026 10:50:00",
    "ssboe": "1776230400",
    "into": "13466.00",
    "inth": "13473.00",
    "intl": "13456.00",
    "intc": "13462.00",
    "intvwap": "13464.04",
    "intv": "2646",
    "intoi": "0",
    "v": "305464",
    "oi": "0"
  },
  {
    "stat": "Ok",
    "time": "15-04-2026 10:51:00",
    "ssboe": "1776230460",
    "into": "13463.00",
    "inth": "13469.00",
    "intl": "13462.00",
    "intc": "13467.00",
    "intvwap": "13466.28",
    "intv": "1585",
    "intoi": "0",
    "v": "307049",
    "oi": "0"
  },
  {
    "stat": "Ok",
    "time": "15-04-2026 10:52:00",
    "ssboe": "1776230520",
    "into": "13465.00",
    "inth": "13465.00",
    "intl": "13435.00",
    "intc": "13436.00",
    "intvwap": "13453.17",
    "intv": "2734",
    "intoi": "0",
    "v": "309783",
    "oi": "0"
  },
  {
    "stat": "Ok",
    "time": "15-04-2026 10:53:00",
    "ssboe": "1776230580",
    "into": "13435.00",
    "inth": "13435.00",
    "intl": "13409.00",
    "intc": "13409.00",
    "intvwap": "13421.35",
    "intv": "2858",
    "intoi": "0",
    "v": "312641",
    "oi": "0"
  },
  {
    "stat": "Ok",
    "time": "15-04-2026 10:54:00",
    "ssboe": "1776230640",
    "into": "13406.00",
    "inth": "13423.00",
    "intl": "13402.00",
    "intc": "13410.00",
    "intvwap": "13412.17",
    "intv": "2496",
    "intoi": "0",
    "v": "315137",
    "oi": "0"
  },
  {
    "stat": "Ok",
    "time": "15-04-2026 10:55:00",
    "ssboe": "1776230700",
    "into": "13411.00",
    "inth": "13419.00",
    "intl": "13405.00",
    "intc": "13419.00",
    "intvwap": "13414.09",
    "intv": "1165",
    "intoi": "0",
    "v": "316302",
    "oi": "0"
  },
  {
    "stat": "Ok",
    "time": "15-04-2026 10:56:00",
    "ssboe": "1776230760",
    "into": "13420.00",
    "inth": "13429.00",
    "intl": "13416.00",
    "intc": "13429.00",
    "intvwap": "13420.70",
    "intv": "1026",
    "intoi": "0",
    "v": "317328",
    "oi": "0"
  },
  {
    "stat": "Ok",
    "time": "15-04-2026 10:57:00",
    "ssboe": "1776230820",
    "into": "13428.00",
    "inth": "13446.00",
    "intl": "13427.00",
    "intc": "13442.00",
    "intvwap": "13434.02",
    "intv": "1611",
    "intoi": "0",
    "v": "318939",
    "oi": "0"
  },
  {
    "stat": "Ok",
    "time": "15-04-2026 10:58:00",
    "ssboe": "1776230880",
    "into": "13444.00",
    "inth": "13451.00",
    "intl": "13442.00",
    "intc": "13451.00",
    "intvwap": "13447.53",
    "intv": "2214",
    "intoi": "0",
    "v": "321153",
    "oi": "0"
  },
  {
    "stat": "Ok",
    "time": "15-04-2026 10:59:00",
    "ssboe": "1776230940",
    "into": "13452.00",
    "inth": "13466.00",
    "intl": "13451.00",
    "intc": "13461.00",
    "intvwap": "13457.72",
    "intv": "1130",
    "intoi": "0",
    "v": "322283",
    "oi": "0"
  },
  {
    "stat": "Ok",
    "time": "15-04-2026 11:00:00",
    "ssboe": "1776231000",
    "into": "13460.00",
    "inth": "13462.00",
    "intl": "13412.00",
    "intc": "13420.00",
    "intvwap": "13440.42",
    "intv": "3998",
    "intoi": "0",
    "v": "326281",
    "oi": "0"
  },
  {
    "stat": "Ok",
    "time": "15-04-2026 11:01:00",
    "ssboe": "1776231060",
    "into": "13426.00",
    "inth": "13427.00",
    "intl": "13421.00",
    "intc": "13424.00",
    "intvwap": "13425.25",
    "intv": "675",
    "intoi": "0",
    "v": "326956",
    "oi": "0"
  },
  {
    "stat": "Ok",
    "time": "15-04-2026 11:02:00",
    "ssboe": "1776231120",
    "into": "13423.00",
    "inth": "13426.00",
    "intl": "13419.00",
    "intc": "13422.00",
    "intvwap": "13421.59",
    "intv": "1554",
    "intoi": "0",
    "v": "328510",
    "oi": "0"
  },
  {
    "stat": "Ok",
    "time": "15-04-2026 11:03:00",
    "ssboe": "1776231180",
    "into": "13423.00",
    "inth": "13423.00",
    "intl": "13411.00",
    "intc": "13414.00",
    "intvwap": "13416.37",
    "intv": "905",
    "intoi": "0",
    "v": "329415",
    "oi": "0"
  },
  {
    "stat": "Ok",
    "time": "15-04-2026 11:04:00",
    "ssboe": "1776231240",
    "into": "13411.00",
    "inth": "13414.00",
    "intl": "13405.00",
    "intc": "13410.00",
    "intvwap": "13407.94",
    "intv": "1810",
    "intoi": "0",
    "v": "331225",
    "oi": "0"
  },
  {
    "stat": "Ok",
    "time": "15-04-2026 11:05:00",
    "ssboe": "1776231300",
    "into": "13405.00",
    "inth": "13410.00",
    "intl": "13405.00",
    "intc": "13408.00",
    "intvwap": "13407.44",
    "intv": "683",
    "intoi": "0",
    "v": "331908",
    "oi": "0"
  },
  {
    "stat": "Ok",
    "time": "15-04-2026 11:06:00",
    "ssboe": "1776231360",
    "into": "13407.00",
    "inth": "13408.00",
    "intl": "13390.00",
    "intc": "13391.00",
    "intvwap": "13398.67",
    "intv": "1989",
    "intoi": "0",
    "v": "333897",
    "oi": "0"
  },
  {
    "stat": "Ok",
    "time": "15-04-2026 11:07:00",
    "ssboe": "1776231420",
    "into": "13390.00",
    "inth": "13390.00",
    "intl": "13372.00",
    "intc": "13372.00",
    "intvwap": "13381.13",
    "intv": "1715",
    "intoi": "0",
    "v": "335612",
    "oi": "0"
  },
  {
    "stat": "Ok",
    "time": "15-04-2026 11:08:00",
    "ssboe": "1776231480",
    "into": "13377.00",
    "inth": "13398.00",
    "intl": "13376.00",
    "intc": "13397.00",
    "intvwap": "13384.84",
    "intv": "2427",
    "intoi": "0",
    "v": "338039",
    "oi": "0"
  },
  {
    "stat": "Ok",
    "time": "15-04-2026 11:09:00",
    "ssboe": "1776231540",
    "into": "13393.00",
    "inth": "13395.00",
    "intl": "13380.00",
    "intc": "13386.00",
    "intvwap": "13383.82",
    "intv": "640",
    "intoi": "0",
    "v": "338679",
    "oi": "0"
  },
  {
    "stat": "Ok",
    "time": "15-04-2026 11:10:00",
    "ssboe": "1776231600",
    "into": "13385.00",
    "inth": "13386.00",
    "intl": "13375.00",
    "intc": "13379.00",
    "intvwap": "13382.38",
    "intv": "793",
    "intoi": "0",
    "v": "339472",
    "oi": "0"
  },
  {
    "stat": "Ok",
    "time": "15-04-2026 11:11:00",
    "ssboe": "1776231660",
    "into": "13375.00",
    "inth": "13387.00",
    "intl": "13375.00",
    "intc": "13387.00",
    "intvwap": "13380.35",
    "intv": "1246",
    "intoi": "0",
    "v": "340718",
    "oi": "0"
  },
  {
    "stat": "Ok",
    "time": "15-04-2026 11:12:00",
    "ssboe": "1776231720",
    "into": "13386.00",
    "inth": "13389.00",
    "intl": "13375.00",
    "intc": "13380.00",
    "intvwap": "13384.58",
    "intv": "962",
    "intoi": "0",
    "v": "341680",
    "oi": "0"
  },
  {
    "stat": "Ok",
    "time": "15-04-2026 11:13:00",
    "ssboe": "1776231780",
    "into": "13379.00",
    "inth": "13380.00",
    "intl": "13373.00",
    "intc": "13375.00",
    "intvwap": "13374.38",
    "intv": "1038",
    "intoi": "0",
    "v": "342718",
    "oi": "0"
  },
  {
    "stat": "Ok",
    "time": "15-04-2026 11:14:00",
    "ssboe": "1776231840",
    "into": "13377.00",
    "inth": "13381.00",
    "intl": "13375.00",
    "intc": "13378.00",
    "intvwap": "13380.20",
    "intv": "919",
    "intoi": "0",
    "v": "343637",
    "oi": "0"
  },
  {
    "stat": "Ok",
    "time": "15-04-2026 11:15:00",
    "ssboe": "1776231900",
    "into": "13379.00",
    "inth": "13380.00",
    "intl": "13367.00",
    "intc": "13378.00",
    "intvwap": "13371.27",
    "intv": "2098",
    "intoi": "0",
    "v": "345735",
    "oi": "0"
  },
  {
    "stat": "Ok",
    "time": "15-04-2026 11:16:00",
    "ssboe": "1776231960",
    "into": "13382.00",
    "inth": "13383.00",
    "intl": "13373.00",
    "intc": "13375.00",
    "intvwap": "13379.80",
    "intv": "942",
    "intoi": "0",
    "v": "346677",
    "oi": "0"
  },
  {
    "stat": "Ok",
    "time": "15-04-2026 11:17:00",
    "ssboe": "1776232020",
    "into": "13376.00",
    "inth": "13381.00",
    "intl": "13375.00",
    "intc": "13378.00",
    "intvwap": "13376.79",
    "intv": "1089",
    "intoi": "0",
    "v": "347766",
    "oi": "0"
  },
  {
    "stat": "Ok",
    "time": "15-04-2026 11:18:00",
    "ssboe": "1776232080",
    "into": "13379.00",
    "inth": "13383.00",
    "intl": "13378.00",
    "intc": "13380.00",
    "intvwap": "13381.08",
    "intv": "1286",
    "intoi": "0",
    "v": "349052",
    "oi": "0"
  },
  {
    "stat": "Ok",
    "time": "15-04-2026 11:19:00",
    "ssboe": "1776232140",
    "into": "13379.00",
    "inth": "13379.00",
    "intl": "13365.00",
    "intc": "13367.00",
    "intvwap": "13371.46",
    "intv": "1436",
    "intoi": "0",
    "v": "350488",
    "oi": "0"
  },
  {
    "stat": "Ok",
    "time": "15-04-2026 11:20:00",
    "ssboe": "1776232200",
    "into": "13361.00",
    "inth": "13382.00",
    "intl": "13361.00",
    "intc": "13381.00",
    "intvwap": "13370.62",
    "intv": "2038",
    "intoi": "0",
    "v": "352526",
    "oi": "0"
  },
  {
    "stat": "Ok",
    "time": "15-04-2026 11:21:00",
    "ssboe": "1776232260",
    "into": "13382.00",
    "inth": "13382.00",
    "intl": "13374.00",
    "intc": "13379.00",
    "intvwap": "13378.30",
    "intv": "543",
    "intoi": "0",
    "v": "353069",
    "oi": "0"
  },
  {
    "stat": "Ok",
    "time": "15-04-2026 11:22:00",
    "ssboe": "1776232320",
    "into": "13374.00",
    "inth": "13386.00",
    "intl": "13374.00",
    "intc": "13386.00",
    "intvwap": "13379.48",
    "intv": "835",
    "intoi": "0",
    "v": "353904",
    "oi": "0"
  },
  {
    "stat": "Ok",
    "time": "15-04-2026 11:23:00",
    "ssboe": "1776232380",
    "into": "13385.00",
    "inth": "13388.00",
    "intl": "13372.00",
    "intc": "13375.00",
    "intvwap": "13382.53",
    "intv": "1290",
    "intoi": "0",
    "v": "355194",
    "oi": "0"
  },
  {
    "stat": "Ok",
    "time": "15-04-2026 11:24:00",
    "ssboe": "1776232440",
    "into": "13373.00",
    "inth": "13375.00",
    "intl": "13365.00",
    "intc": "13369.00",
    "intvwap": "13368.44",
    "intv": "807",
    "intoi": "0",
    "v": "356001",
    "oi": "0"
  },
  {
    "stat": "Ok",
    "time": "15-04-2026 11:25:00",
    "ssboe": "1776232500",
    "into": "13370.00",
    "inth": "13371.00",
    "intl": "13367.00",
    "intc": "13369.00",
    "intvwap": "13367.00",
    "intv": "1167",
    "intoi": "0",
    "v": "357168",
    "oi": "0"
  },
  {
    "stat": "Ok",
    "time": "15-04-2026 11:26:00",
    "ssboe": "1776232560",
    "into": "13368.00",
    "inth": "13368.00",
    "intl": "13355.00",
    "intc": "13360.00",
    "intvwap": "13362.81",
    "intv": "1338",
    "intoi": "0",
    "v": "358506",
    "oi": "0"
  },
  {
    "stat": "Ok",
    "time": "15-04-2026 11:27:00",
    "ssboe": "1776232620",
    "into": "13358.00",
    "inth": "13369.00",
    "intl": "13355.00",
    "intc": "13369.00",
    "intvwap": "13361.04",
    "intv": "1304",
    "intoi": "0",
    "v": "359810",
    "oi": "0"
  },
  {
    "stat": "Ok",
    "time": "15-04-2026 11:28:00",
    "ssboe": "1776232680",
    "into": "13368.00",
    "inth": "13368.00",
    "intl": "13347.00",
    "intc": "13355.00",
    "intvwap": "13352.75",
    "intv": "5130",
    "intoi": "0",
    "v": "364940",
    "oi": "0"
  },
  {
    "stat": "Ok",
    "time": "15-04-2026 11:29:00",
    "ssboe": "1776232740",
    "into": "13357.00",
    "inth": "13357.00",
    "intl": "13350.00",
    "intc": "13355.00",
    "intvwap": "13350.00",
    "intv": "719",
    "intoi": "0",
    "v": "365659",
    "oi": "0"
  },
  {
    "stat": "Ok",
    "time": "15-04-2026 11:30:00",
    "ssboe": "1776232800",
    "into": "13354.00",
    "inth": "13369.00",
    "intl": "13354.00",
    "intc": "13359.00",
    "intvwap": "13363.09",
    "intv": "1003",
    "intoi": "0",
    "v": "366662",
    "oi": "0"
  },
  {
    "stat": "Ok",
    "time": "15-04-2026 11:31:00",
    "ssboe": "1776232860",
    "into": "13362.00",
    "inth": "13364.00",
    "intl": "13355.00",
    "intc": "13363.00",
    "intvwap": "13359.11",
    "intv": "1022",
    "intoi": "0",
    "v": "367684",
    "oi": "0"
  },
  {
    "stat": "Ok",
    "time": "15-04-2026 11:32:00",
    "ssboe": "1776232920",
    "into": "13365.00",
    "inth": "13367.00",
    "intl": "13354.00",
    "intc": "13354.00",
    "intvwap": "13357.66",
    "intv": "1247",
    "intoi": "0",
    "v": "368931",
    "oi": "0"
  },
  {
    "stat": "Ok",
    "time": "15-04-2026 11:33:00",
    "ssboe": "1776232980",
    "into": "13352.00",
    "inth": "13355.00",
    "intl": "13350.00",
    "intc": "13355.00",
    "intvwap": "13351.87",
    "intv": "831",
    "intoi": "0",
    "v": "369762",
    "oi": "0"
  },
  {
    "stat": "Ok",
    "time": "15-04-2026 11:34:00",
    "ssboe": "1776233040",
    "into": "13354.00",
    "inth": "13359.00",
    "intl": "13354.00",
    "intc": "13354.00",
    "intvwap": "13357.84",
    "intv": "781",
    "intoi": "0",
    "v": "370543",
    "oi": "0"
  },
  {
    "stat": "Ok",
    "time": "15-04-2026 11:35:00",
    "ssboe": "1776233100",
    "into": "13355.00",
    "inth": "13369.00",
    "intl": "13353.00",
    "intc": "13365.00",
    "intvwap": "13360.50",
    "intv": "1129",
    "intoi": "0",
    "v": "371672",
    "oi": "0"
  },
  {
    "stat": "Ok",
    "time": "15-04-2026 11:36:00",
    "ssboe": "1776233160",
    "into": "13362.00",
    "inth": "13365.00",
    "intl": "13361.00",
    "intc": "13364.00",
    "intvwap": "13362.82",
    "intv": "521",
    "intoi": "0",
    "v": "372193",
    "oi": "0"
  },
  {
    "stat": "Ok",
    "time": "15-04-2026 11:37:00",
    "ssboe": "1776233220",
    "into": "13367.00",
    "inth": "13367.00",
    "intl": "13362.00",
    "intc": "13364.00",
    "intvwap": "13367.00",
    "intv": "569",
    "intoi": "0",
    "v": "372762",
    "oi": "0"
  },
  {
    "stat": "Ok",
    "time": "15-04-2026 11:38:00",
    "ssboe": "1776233280",
    "into": "13363.00",
    "inth": "13364.00",
    "intl": "13362.00",
    "intc": "13363.00",
    "intvwap": "13362.00",
    "intv": "407",
    "intoi": "0",
    "v": "373169",
    "oi": "0"
  },
  {
    "stat": "Ok",
    "time": "15-04-2026 11:39:00",
    "ssboe": "1776233340",
    "into": "13362.00",
    "inth": "13363.00",
    "intl": "13350.00",
    "intc": "13350.00",
    "intvwap": "13356.70",
    "intv": "1678",
    "intoi": "0",
    "v": "374847",
    "oi": "0"
  },
  {
    "stat": "Ok",
    "time": "15-04-2026 11:40:00",
    "ssboe": "1776233400",
    "into": "13351.00",
    "inth": "13356.00",
    "intl": "13333.00",
    "intc": "13348.00",
    "intvwap": "13344.25",
    "intv": "3869",
    "intoi": "0",
    "v": "378716",
    "oi": "0"
  },
  {
    "stat": "Ok",
    "time": "15-04-2026 11:41:00",
    "ssboe": "1776233460",
    "into": "13345.00",
    "inth": "13348.00",
    "intl": "13339.00",
    "intc": "13340.00",
    "intvwap": "13345.06",
    "intv": "723",
    "intoi": "0",
    "v": "379439",
    "oi": "0"
  },
  {
    "stat": "Ok",
    "time": "15-04-2026 11:42:00",
    "ssboe": "1776233520",
    "into": "13342.00",
    "inth": "13342.00",
    "intl": "13336.00",
    "intc": "13337.00",
    "intvwap": "13336.00",
    "intv": "558",
    "intoi": "0",
    "v": "379997",
    "oi": "0"
  },
  {
    "stat": "Ok",
    "time": "15-04-2026 11:43:00",
    "ssboe": "1776233580",
    "into": "13338.00",
    "inth": "13352.00",
    "intl": "13337.00",
    "intc": "13338.00",
    "intvwap": "13343.68",
    "intv": "1257",
    "intoi": "0",
    "v": "381254",
    "oi": "0"
  },
  {
    "stat": "Ok",
    "time": "15-04-2026 11:44:00",
    "ssboe": "1776233640",
    "into": "13337.00",
    "inth": "13346.00",
    "intl": "13336.00",
    "intc": "13341.00",
    "intvwap": "13339.51",
    "intv": "781",
    "intoi": "0",
    "v": "382035",
    "oi": "0"
  },
  {
    "stat": "Ok",
    "time": "15-04-2026 11:45:00",
    "ssboe": "1776233700",
    "into": "13342.00",
    "inth": "13345.00",
    "intl": "13332.00",
    "intc": "13333.00",
    "intvwap": "13338.25",
    "intv": "1058",
    "intoi": "0",
    "v": "383093",
    "oi": "0"
  },
  {
    "stat": "Ok",
    "time": "15-04-2026 11:46:00",
    "ssboe": "1776233760",
    "into": "13335.00",
    "inth": "13348.00",
    "intl": "13334.00",
    "intc": "13334.00",
    "intvwap": "13339.24",
    "intv": "834",
    "intoi": "0",
    "v": "383927",
    "oi": "0"
  },
  {
    "stat": "Ok",
    "time": "15-04-2026 11:47:00",
    "ssboe": "1776233820",
    "into": "13339.00",
    "inth": "13339.00",
    "intl": "13334.00",
    "intc": "13336.00",
    "intvwap": "13334.65",
    "intv": "453",
    "intoi": "0",
    "v": "384380",
    "oi": "0"
  },
  {
    "stat": "Ok",
    "time": "15-04-2026 11:48:00",
    "ssboe": "1776233880",
    "into": "13337.00",
    "inth": "13337.00",
    "intl": "13332.00",
    "intc": "13332.00",
    "intvwap": "13337.00",
    "intv": "612",
    "intoi": "0",
    "v": "384992",
    "oi": "0"
  },
  {
    "stat": "Ok",
    "time": "15-04-2026 11:49:00",
    "ssboe": "1776233940",
    "into": "13335.00",
    "inth": "13345.00",
    "intl": "13333.00",
    "intc": "13342.00",
    "intvwap": "13334.66",
    "intv": "837",
    "intoi": "0",
    "v": "385829",
    "oi": "0"
  },
  {
    "stat": "Ok",
    "time": "15-04-2026 11:50:00",
    "ssboe": "1776234000",
    "into": "13341.00",
    "inth": "13343.00",
    "intl": "13330.00",
    "intc": "13331.00",
    "intvwap": "13337.53",
    "intv": "1345",
    "intoi": "0",
    "v": "387174",
    "oi": "0"
  },
  {
    "stat": "Ok",
    "time": "15-04-2026 11:51:00",
    "ssboe": "1776234060",
    "into": "13330.00",
    "inth": "13335.00",
    "intl": "13330.00",
    "intc": "13334.00",
    "intvwap": "13330.00",
    "intv": "726",
    "intoi": "0",
    "v": "387900",
    "oi": "0"
  },
  {
    "stat": "Ok",
    "time": "15-04-2026 11:52:00",
    "ssboe": "1776234120",
    "into": "13333.00",
    "inth": "13341.00",
    "intl": "13332.00",
    "intc": "13340.00",
    "intvwap": "13337.98",
    "intv": "1170",
    "intoi": "0",
    "v": "389070",
    "oi": "0"
  },
  {
    "stat": "Ok",
    "time": "15-04-2026 11:53:00",
    "ssboe": "1776234180",
    "into": "13339.00",
    "inth": "13349.00",
    "intl": "13338.00",
    "intc": "13349.00",
    "intvwap": "13344.29",
    "intv": "1217",
    "intoi": "0",
    "v": "390287",
    "oi": "0"
  },
  {
    "stat": "Ok",
    "time": "15-04-2026 11:54:00",
    "ssboe": "1776234240",
    "into": "13347.00",
    "inth": "13353.00",
    "intl": "13338.00",
    "intc": "13350.00",
    "intvwap": "13346.67",
    "intv": "1308",
    "intoi": "0",
    "v": "391595",
    "oi": "0"
  },
  {
    "stat": "Ok",
    "time": "15-04-2026 11:55:00",
    "ssboe": "1776234300",
    "into": "13352.00",
    "inth": "13352.00",
    "intl": "13342.00",
    "intc": "13351.00",
    "intvwap": "13346.56",
    "intv": "996",
    "intoi": "0",
    "v": "392591",
    "oi": "0"
  },
  {
    "stat": "Ok",
    "time": "15-04-2026 11:56:00",
    "ssboe": "1776234360",
    "into": "13349.00",
    "inth": "13360.00",
    "intl": "13347.00",
    "intc": "13349.00",
    "intvwap": "13354.56",
    "intv": "1793",
    "intoi": "0",
    "v": "394384",
    "oi": "0"
  },
  {
    "stat": "Ok",
    "time": "15-04-2026 11:57:00",
    "ssboe": "1776234420",
    "into": "13348.00",
    "inth": "13348.00",
    "intl": "13340.00",
    "intc": "13340.00",
    "intvwap": "13343.55",
    "intv": "909",
    "intoi": "0",
    "v": "395293",
    "oi": "0"
  },
  {
    "stat": "Ok",
    "time": "15-04-2026 11:58:00",
    "ssboe": "1776234480",
    "into": "13341.00",
    "inth": "13351.00",
    "intl": "13335.00",
    "intc": "13346.00",
    "intvwap": "13344.13",
    "intv": "1285",
    "intoi": "0",
    "v": "396578",
    "oi": "0"
  },
  {
    "stat": "Ok",
    "time": "15-04-2026 11:59:00",
    "ssboe": "1776234540",
    "into": "13348.00",
    "inth": "13353.00",
    "intl": "13347.00",
    "intc": "13351.00",
    "intvwap": "13353.00",
    "intv": "657",
    "intoi": "0",
    "v": "397235",
    "oi": "0"
  },
  {
    "stat": "Ok",
    "time": "15-04-2026 12:00:00",
    "ssboe": "1776234600",
    "into": "13350.00",
    "inth": "13351.00",
    "intl": "13345.00",
    "intc": "13345.00",
    "intvwap": "13348.34",
    "intv": "891",
    "intoi": "0",
    "v": "398126",
    "oi": "0"
  },
  {
    "stat": "Ok",
    "time": "15-04-2026 12:01:00",
    "ssboe": "1776234660",
    "into": "13346.00",
    "inth": "13346.00",
    "intl": "13340.00",
    "intc": "13342.00",
    "intvwap": "13346.00",
    "intv": "650",
    "intoi": "0",
    "v": "398776",
    "oi": "0"
  },
  {
    "stat": "Ok",
    "time": "15-04-2026 12:02:00",
    "ssboe": "1776234720",
    "into": "13344.00",
    "inth": "13357.00",
    "intl": "13342.00",
    "intc": "13350.00",
    "intvwap": "13344.80",
    "intv": "814",
    "intoi": "0",
    "v": "399590",
    "oi": "0"
  },
  {
    "stat": "Ok",
    "time": "15-04-2026 12:03:00",
    "ssboe": "1776234780",
    "into": "13349.00",
    "inth": "13349.00",
    "intl": "13345.00",
    "intc": "13346.00",
    "intvwap": "13349.00",
    "intv": "431",
    "intoi": "0",
    "v": "400021",
    "oi": "0"
  },
  {
    "stat": "Ok",
    "time": "15-04-2026 12:04:00",
    "ssboe": "1776234840",
    "into": "13345.00",
    "inth": "13356.00",
    "intl": "13345.00",
    "intc": "13352.00",
    "intvwap": "13347.36",
    "intv": "975",
    "intoi": "0",
    "v": "400996",
    "oi": "0"
  },
  {
    "stat": "Ok",
    "time": "15-04-2026 12:05:00",
    "ssboe": "1776234900",
    "into": "13353.00",
    "inth": "13360.00",
    "intl": "13351.00",
    "intc": "13351.00",
    "intvwap": "13360.00",
    "intv": "785",
    "intoi": "0",
    "v": "401781",
    "oi": "0"
  },
  {
    "stat": "Ok",
    "time": "15-04-2026 12:06:00",
    "ssboe": "1776234960",
    "into": "13350.00",
    "inth": "13351.00",
    "intl": "13341.00",
    "intc": "13344.00",
    "intvwap": "13343.17",
    "intv": "499",
    "intoi": "0",
    "v": "402280",
    "oi": "0"
  },
  {
    "stat": "Ok",
    "time": "15-04-2026 12:07:00",
    "ssboe": "1776235020",
    "into": "13341.00",
    "inth": "13341.00",
    "intl": "13330.00",
    "intc": "13333.00",
    "intvwap": "13335.12",
    "intv": "977",
    "intoi": "0",
    "v": "403257",
    "oi": "0"
  },
  {
    "stat": "Ok",
    "time": "15-04-2026 12:08:00",
    "ssboe": "1776235080",
    "into": "13331.00",
    "inth": "13341.00",
    "intl": "13331.00",
    "intc": "13333.00",
    "intvwap": "13335.12",
    "intv": "786",
    "intoi": "0",
    "v": "404043",
    "oi": "0"
  },
  {
    "stat": "Ok",
    "time": "15-04-2026 12:09:00",
    "ssboe": "1776235140",
    "into": "13332.00",
    "inth": "13333.00",
    "intl": "13325.00",
    "intc": "13329.00",
    "intvwap": "13326.50",
    "intv": "2835",
    "intoi": "0",
    "v": "406878",
    "oi": "0"
  },
  {
    "stat": "Ok",
    "time": "15-04-2026 12:10:00",
    "ssboe": "1776235200",
    "into": "13327.00",
    "inth": "13339.00",
    "intl": "13325.00",
    "intc": "13339.00",
    "intvwap": "13335.06",
    "intv": "862",
    "intoi": "0",
    "v": "407740",
    "oi": "0"
  },
  {
    "stat": "Ok",
    "time": "15-04-2026 12:11:00",
    "ssboe": "1776235260",
    "into": "13338.00",
    "inth": "13339.00",
    "intl": "13333.00",
    "intc": "13335.00",
    "intvwap": "13335.06",
    "intv": "329",
    "intoi": "0",
    "v": "408069",
    "oi": "0"
  },
  {
    "stat": "Ok",
    "time": "15-04-2026 12:12:00",
    "ssboe": "1776235320",
    "into": "13333.00",
    "inth": "13348.00",
    "intl": "13330.00",
    "intc": "13346.00",
    "intvwap": "13338.39",
    "intv": "1227",
    "intoi": "0",
    "v": "409296",
    "oi": "0"
  },
  {
    "stat": "Ok",
    "time": "15-04-2026 12:13:00",
    "ssboe": "1776235380",
    "into": "13345.00",
    "inth": "13346.00",
    "intl": "13339.00",
    "intc": "13339.00",
    "intvwap": "13344.84",
    "intv": "419",
    "intoi": "0",
    "v": "409715",
    "oi": "0"
  },
  {
    "stat": "Ok",
    "time": "15-04-2026 12:14:00",
    "ssboe": "1776235440",
    "into": "13340.00",
    "inth": "13347.00",
    "intl": "13340.00",
    "intc": "13343.00",
    "intvwap": "13347.00",
    "intv": "4091",
    "intoi": "0",
    "v": "413806",
    "oi": "0"
  },
  {
    "stat": "Ok",
    "time": "15-04-2026 12:15:00",
    "ssboe": "1776235500",
    "into": "13345.00",
    "inth": "13345.00",
    "intl": "13339.00",
    "intc": "13339.00",
    "intvwap": "13343.22",
    "intv": "516",
    "intoi": "0",
    "v": "414322",
    "oi": "0"
  },
  {
    "stat": "Ok",
    "time": "15-04-2026 12:16:00",
    "ssboe": "1776235560",
    "into": "13342.00",
    "inth": "13342.00",
    "intl": "13334.00",
    "intc": "13334.00",
    "intvwap": "13341.72",
    "intv": "637",
    "intoi": "0",
    "v": "414959",
    "oi": "0"
  },
  {
    "stat": "Ok",
    "time": "15-04-2026 12:17:00",
    "ssboe": "1776235620",
    "into": "13338.00",
    "inth": "13345.00",
    "intl": "13330.00",
    "intc": "13336.00",
    "intvwap": "13335.22",
    "intv": "840",
    "intoi": "0",
    "v": "415799",
    "oi": "0"
  },
  {
    "stat": "Ok",
    "time": "15-04-2026 12:18:00",
    "ssboe": "1776235680",
    "into": "13335.00",
    "inth": "13336.00",
    "intl": "13330.00",
    "intc": "13335.00",
    "intvwap": "13335.22",
    "intv": "704",
    "intoi": "0",
    "v": "416503",
    "oi": "0"
  },
  {
    "stat": "Ok",
    "time": "15-04-2026 12:19:00",
    "ssboe": "1776235740",
    "into": "13334.00",
    "inth": "13336.00",
    "intl": "13333.00",
    "intc": "13336.00",
    "intvwap": "13335.22",
    "intv": "689",
    "intoi": "0",
    "v": "417192",
    "oi": "0"
  },
  {
    "stat": "Ok",
    "time": "15-04-2026 12:20:00",
    "ssboe": "1776235800",
    "into": "13335.00",
    "inth": "13347.00",
    "intl": "13335.00",
    "intc": "13343.00",
    "intvwap": "13340.64",
    "intv": "770",
    "intoi": "0",
    "v": "417962",
    "oi": "0"
  },
  {
    "stat": "Ok",
    "time": "15-04-2026 12:21:00",
    "ssboe": "1776235860",
    "into": "13342.00",
    "inth": "13343.00",
    "intl": "13324.00",
    "intc": "13324.00",
    "intvwap": "13331.64",
    "intv": "1170",
    "intoi": "0",
    "v": "419132",
    "oi": "0"
  },
  {
    "stat": "Ok",
    "time": "15-04-2026 12:22:00",
    "ssboe": "1776235920",
    "into": "13323.00",
    "inth": "13325.00",
    "intl": "13319.00",
    "intc": "13319.00",
    "intvwap": "13321.86",
    "intv": "1892",
    "intoi": "0",
    "v": "421024",
    "oi": "0"
  },
  {
    "stat": "Ok",
    "time": "15-04-2026 12:23:00",
    "ssboe": "1776235980",
    "into": "13322.00",
    "inth": "13329.00",
    "intl": "13320.00",
    "intc": "13329.00",
    "intvwap": "13327.29",
    "intv": "536",
    "intoi": "0",
    "v": "421560",
    "oi": "0"
  },
  {
    "stat": "Ok",
    "time": "15-04-2026 12:24:00",
    "ssboe": "1776236040",
    "into": "13327.00",
    "inth": "13339.00",
    "intl": "13327.00",
    "intc": "13338.00",
    "intvwap": "13335.15",
    "intv": "1088",
    "intoi": "0",
    "v": "422648",
    "oi": "0"
  },
  {
    "stat": "Ok",
    "time": "15-04-2026 12:25:00",
    "ssboe": "1776236100",
    "into": "13336.00",
    "inth": "13352.00",
    "intl": "13336.00",
    "intc": "13351.00",
    "intvwap": "13345.33",
    "intv": "1248",
    "intoi": "0",
    "v": "423896",
    "oi": "0"
  },
  {
    "stat": "Ok",
    "time": "15-04-2026 12:26:00",
    "ssboe": "1776236160",
    "into": "13350.00",
    "inth": "13365.00",
    "intl": "13350.00",
    "intc": "13350.00",
    "intvwap": "13357.18",
    "intv": "1547",
    "intoi": "0",
    "v": "425443",
    "oi": "0"
  },
  {
    "stat": "Ok",
    "time": "15-04-2026 12:27:00",
    "ssboe": "1776236220",
    "into": "13352.00",
    "inth": "13357.00",
    "intl": "13342.00",
    "intc": "13344.00",
    "intvwap": "13345.90",
    "intv": "801",
    "intoi": "0",
    "v": "426244",
    "oi": "0"
  },
  {
    "stat": "Ok",
    "time": "15-04-2026 12:28:00",
    "ssboe": "1776236280",
    "into": "13346.00",
    "inth": "13352.00",
    "intl": "13345.00",
    "intc": "13349.00",
    "intvwap": "13351.50",
    "intv": "526",
    "intoi": "0",
    "v": "426770",
    "oi": "0"
  },
  {
    "stat": "Ok",
    "time": "15-04-2026 12:29:00",
    "ssboe": "1776236340",
    "into": "13347.00",
    "inth": "13350.00",
    "intl": "13342.00",
    "intc": "13345.00",
    "intvwap": "13350.00",
    "intv": "573",
    "intoi": "0",
    "v": "427343",
    "oi": "0"
  },
  {
    "stat": "Ok",
    "time": "15-04-2026 12:30:00",
    "ssboe": "1776236400",
    "into": "13341.00",
    "inth": "13345.00",
    "intl": "13334.00",
    "intc": "13339.00",
    "intvwap": "13341.32",
    "intv": "713",
    "intoi": "0",
    "v": "428056",
    "oi": "0"
  },
  {
    "stat": "Ok",
    "time": "15-04-2026 12:31:00",
    "ssboe": "1776236460",
    "into": "13337.00",
    "inth": "13337.00",
    "intl": "13317.00",
    "intc": "13318.00",
    "intvwap": "13327.21",
    "intv": "1588",
    "intoi": "0",
    "v": "429644",
    "oi": "0"
  },
  {
    "stat": "Ok",
    "time": "15-04-2026 12:32:00",
    "ssboe": "1776236520",
    "into": "13320.00",
    "inth": "13326.00",
    "intl": "13308.00",
    "intc": "13312.00",
    "intvwap": "13316.54",
    "intv": "1841",
    "intoi": "0",
    "v": "431485",
    "oi": "0"
  },
  {
    "stat": "Ok",
    "time": "15-04-2026 12:33:00",
    "ssboe": "1776236580",
    "into": "13311.00",
    "inth": "13318.00",
    "intl": "13310.00",
    "intc": "13315.00",
    "intvwap": "13316.32",
    "intv": "1145",
    "intoi": "0",
    "v": "432630",
    "oi": "0"
  },
  {
    "stat": "Ok",
    "time": "15-04-2026 12:34:00",
    "ssboe": "1776236640",
    "into": "13314.00",
    "inth": "13320.00",
    "intl": "13309.00",
    "intc": "13317.00",
    "intvwap": "13309.00",
    "intv": "798",
    "intoi": "0",
    "v": "433428",
    "oi": "0"
  },
  {
    "stat": "Ok",
    "time": "15-04-2026 12:35:00",
    "ssboe": "1776236700",
    "into": "13316.00",
    "inth": "13326.00",
    "intl": "13315.00",
    "intc": "13326.00",
    "intvwap": "13325.51",
    "intv": "904",
    "intoi": "0",
    "v": "434332",
    "oi": "0"
  },
  {
    "stat": "Ok",
    "time": "15-04-2026 12:36:00",
    "ssboe": "1776236760",
    "into": "13323.00",
    "inth": "13332.00",
    "intl": "13323.00",
    "intc": "13331.00",
    "intvwap": "13326.01",
    "intv": "958",
    "intoi": "0",
    "v": "435290",
    "oi": "0"
  },
  {
    "stat": "Ok",
    "time": "15-04-2026 12:37:00",
    "ssboe": "1776236820",
    "into": "13328.00",
    "inth": "13330.00",
    "intl": "13319.00",
    "intc": "13324.00",
    "intvwap": "13322.62",
    "intv": "700",
    "intoi": "0",
    "v": "435990",
    "oi": "0"
  },
  {
    "stat": "Ok",
    "time": "15-04-2026 12:38:00",
    "ssboe": "1776236880",
    "into": "13321.00",
    "inth": "13324.00",
    "intl": "13321.00",
    "intc": "13322.00",
    "intvwap": "13324.00",
    "intv": "588",
    "intoi": "0",
    "v": "436578",
    "oi": "0"
  },
  {
    "stat": "Ok",
    "time": "15-04-2026 12:39:00",
    "ssboe": "1776236940",
    "into": "13321.00",
    "inth": "13322.00",
    "intl": "13320.00",
    "intc": "13321.00",
    "intvwap": "13322.00",
    "intv": "673",
    "intoi": "0",
    "v": "437251",
    "oi": "0"
  },
  {
    "stat": "Ok",
    "time": "15-04-2026 12:40:00",
    "ssboe": "1776237000",
    "into": "13320.00",
    "inth": "13326.00",
    "intl": "13320.00",
    "intc": "13322.00",
    "intvwap": "13320.00",
    "intv": "789",
    "intoi": "0",
    "v": "438040",
    "oi": "0"
  },
  {
    "stat": "Ok",
    "time": "15-04-2026 12:41:00",
    "ssboe": "1776237060",
    "into": "13320.00",
    "inth": "13333.00",
    "intl": "13320.00",
    "intc": "13328.00",
    "intvwap": "13324.64",
    "intv": "848",
    "intoi": "0",
    "v": "438888",
    "oi": "0"
  },
  {
    "stat": "Ok",
    "time": "15-04-2026 12:42:00",
    "ssboe": "1776237120",
    "into": "13326.00",
    "inth": "13328.00",
    "intl": "13320.00",
    "intc": "13323.00",
    "intvwap": "13328.00",
    "intv": "665",
    "intoi": "0",
    "v": "439553",
    "oi": "0"
  },
  {
    "stat": "Ok",
    "time": "15-04-2026 12:43:00",
    "ssboe": "1776237180",
    "into": "13321.00",
    "inth": "13322.00",
    "intl": "13315.00",
    "intc": "13317.00",
    "intvwap": "13320.72",
    "intv": "618",
    "intoi": "0",
    "v": "440171",
    "oi": "0"
  },
  {
    "stat": "Ok",
    "time": "15-04-2026 12:44:00",
    "ssboe": "1776237240",
    "into": "13316.00",
    "inth": "13321.00",
    "intl": "13313.00",
    "intc": "13313.00",
    "intvwap": "13316.63",
    "intv": "722",
    "intoi": "0",
    "v": "440893",
    "oi": "0"
  },
  {
    "stat": "Ok",
    "time": "15-04-2026 12:45:00",
    "ssboe": "1776237300",
    "into": "13317.00",
    "inth": "13324.00",
    "intl": "13313.00",
    "intc": "13324.00",
    "intvwap": "13318.95",
    "intv": "830",
    "intoi": "0",
    "v": "441723",
    "oi": "0"
  },
  {
    "stat": "Ok",
    "time": "15-04-2026 12:46:00",
    "ssboe": "1776237360",
    "into": "13323.00",
    "inth": "13326.00",
    "intl": "13320.00",
    "intc": "13320.00",
    "intvwap": "13322.96",
    "intv": "1114",
    "intoi": "0",
    "v": "442837",
    "oi": "0"
  },
  {
    "stat": "Ok",
    "time": "15-04-2026 12:47:00",
    "ssboe": "1776237420",
    "into": "13322.00",
    "inth": "13322.00",
    "intl": "13312.00",
    "intc": "13314.00",
    "intvwap": "13312.46",
    "intv": "594",
    "intoi": "0",
    "v": "443431",
    "oi": "0"
  },
  {
    "stat": "Ok",
    "time": "15-04-2026 12:48:00",
    "ssboe": "1776237480",
    "into": "13312.00",
    "inth": "13316.00",
    "intl": "13312.00",
    "intc": "13314.00",
    "intvwap": "13313.78",
    "intv": "633",
    "intoi": "0",
    "v": "444064",
    "oi": "0"
  },
  {
    "stat": "Ok",
    "time": "15-04-2026 12:49:00",
    "ssboe": "1776237540",
    "into": "13313.00",
    "inth": "13314.00",
    "intl": "13309.00",
    "intc": "13313.00",
    "intvwap": "13312.07",
    "intv": "783",
    "intoi": "0",
    "v": "444847",
    "oi": "0"
  },
  {
    "stat": "Ok",
    "time": "15-04-2026 12:50:00",
    "ssboe": "1776237600",
    "into": "13314.00",
    "inth": "13316.00",
    "intl": "13313.00",
    "intc": "13313.00",
    "intvwap": "13316.00",
    "intv": "503",
    "intoi": "0",
    "v": "445350",
    "oi": "0"
  },
  {
    "stat": "Ok",
    "time": "15-04-2026 12:51:00",
    "ssboe": "1776237660",
    "into": "13312.00",
    "inth": "13321.00",
    "intl": "13312.00",
    "intc": "13319.00",
    "intvwap": "13312.97",
    "intv": "820",
    "intoi": "0",
    "v": "446170",
    "oi": "0"
  },
  {
    "stat": "Ok",
    "time": "15-04-2026 12:52:00",
    "ssboe": "1776237720",
    "into": "13318.00",
    "inth": "13321.00",
    "intl": "13316.00",
    "intc": "13319.00",
    "intvwap": "13319.73",
    "intv": "597",
    "intoi": "0",
    "v": "446767",
    "oi": "0"
  },
  {
    "stat": "Ok",
    "time": "15-04-2026 12:53:00",
    "ssboe": "1776237780",
    "into": "13321.00",
    "inth": "13321.00",
    "intl": "13301.00",
    "intc": "13304.00",
    "intvwap": "13312.19",
    "intv": "1395",
    "intoi": "0",
    "v": "448162",
    "oi": "0"
  },
  {
    "stat": "Ok",
    "time": "15-04-2026 12:54:00",
    "ssboe": "1776237840",
    "into": "13307.00",
    "inth": "13308.00",
    "intl": "13304.00",
    "intc": "13306.00",
    "intvwap": "13306.29",
    "intv": "634",
    "intoi": "0",
    "v": "448796",
    "oi": "0"
  },
  {
    "stat": "Ok",
    "time": "15-04-2026 12:55:00",
    "ssboe": "1776237900",
    "into": "13307.00",
    "inth": "13315.00",
    "intl": "13307.00",
    "intc": "13314.00",
    "intvwap": "13309.42",
    "intv": "715",
    "intoi": "0",
    "v": "449511",
    "oi": "0"
  },
  {
    "stat": "Ok",
    "time": "15-04-2026 12:56:00",
    "ssboe": "1776237960",
    "into": "13315.00",
    "inth": "13316.00",
    "intl": "13309.00",
    "intc": "13313.00",
    "intvwap": "13309.00",
    "intv": "337",
    "intoi": "0",
    "v": "449848",
    "oi": "0"
  },
  {
    "stat": "Ok",
    "time": "15-04-2026 12:57:00",
    "ssboe": "1776238020",
    "into": "13312.00",
    "inth": "13320.00",
    "intl": "13312.00",
    "intc": "13316.00",
    "intvwap": "13315.74",
    "intv": "961",
    "intoi": "0",
    "v": "450809",
    "oi": "0"
  },
  {
    "stat": "Ok",
    "time": "15-04-2026 12:58:00",
    "ssboe": "1776238080",
    "into": "13319.00",
    "inth": "13319.00",
    "intl": "13306.00",
    "intc": "13309.00",
    "intvwap": "13316.30",
    "intv": "497",
    "intoi": "0",
    "v": "451306",
    "oi": "0"
  },
  {
    "stat": "Ok",
    "time": "15-04-2026 12:59:00",
    "ssboe": "1776238140",
    "into": "13307.00",
    "inth": "13312.00",
    "intl": "13306.00",
    "intc": "13312.00",
    "intvwap": "13310.06",
    "intv": "556",
    "intoi": "0",
    "v": "451862",
    "oi": "0"
  },
  {
    "stat": "Ok",
    "time": "15-04-2026 13:00:00",
    "ssboe": "1776238200",
    "into": "13309.00",
    "inth": "13309.00",
    "intl": "13302.00",
    "intc": "13302.00",
    "intvwap": "13302.00",
    "intv": "971",
    "intoi": "0",
    "v": "452833",
    "oi": "0"
  },
  {
    "stat": "Ok",
    "time": "15-04-2026 13:01:00",
    "ssboe": "1776238260",
    "into": "13303.00",
    "inth": "13312.00",
    "intl": "13302.00",
    "intc": "13306.00",
    "intvwap": "13302.00",
    "intv": "3157",
    "intoi": "0",
    "v": "455990",
    "oi": "0"
  },
  {
    "stat": "Ok",
    "time": "15-04-2026 13:02:00",
    "ssboe": "1776238320",
    "into": "13307.00",
    "inth": "13308.00",
    "intl": "13300.00",
    "intc": "13307.00",
    "intvwap": "13306.69",
    "intv": "833",
    "intoi": "0",
    "v": "456823",
    "oi": "0"
  },
  {
    "stat": "Ok",
    "time": "15-04-2026 13:03:00",
    "ssboe": "1776238380",
    "into": "13305.00",
    "inth": "13309.00",
    "intl": "13303.00",
    "intc": "13306.00",
    "intvwap": "13307.15",
    "intv": "680",
    "intoi": "0",
    "v": "457503",
    "oi": "0"
  },
  {
    "stat": "Ok",
    "time": "15-04-2026 13:04:00",
    "ssboe": "1776238440",
    "into": "13305.00",
    "inth": "13308.00",
    "intl": "13305.00",
    "intc": "13308.00",
    "intvwap": "13307.92",
    "intv": "702",
    "intoi": "0",
    "v": "458205",
    "oi": "0"
  },
  {
    "stat": "Ok",
    "time": "15-04-2026 13:05:00",
    "ssboe": "1776238500",
    "into": "13306.00",
    "inth": "13307.00",
    "intl": "13300.00",
    "intc": "13301.00",
    "intvwap": "13301.31",
    "intv": "3106",
    "intoi": "0",
    "v": "461311",
    "oi": "0"
  },
  {
    "stat": "Ok",
    "time": "15-04-2026 13:06:00",
    "ssboe": "1776238560",
    "into": "13300.00",
    "inth": "13311.00",
    "intl": "13300.00",
    "intc": "13311.00",
    "intvwap": "13302.90",
    "intv": "1349",
    "intoi": "0",
    "v": "462660",
    "oi": "0"
  },
  {
    "stat": "Ok",
    "time": "15-04-2026 13:07:00",
    "ssboe": "1776238620",
    "into": "13312.00",
    "inth": "13316.00",
    "intl": "13311.00",
    "intc": "13311.00",
    "intvwap": "13313.54",
    "intv": "1152",
    "intoi": "0",
    "v": "463812",
    "oi": "0"
  },
  {
    "stat": "Ok",
    "time": "15-04-2026 13:08:00",
    "ssboe": "1776238680",
    "into": "13309.00",
    "inth": "13312.00",
    "intl": "13305.00",
    "intc": "13311.00",
    "intvwap": "13307.67",
    "intv": "716",
    "intoi": "0",
    "v": "464528",
    "oi": "0"
  },
  {
    "stat": "Ok",
    "time": "15-04-2026 13:09:00",
    "ssboe": "1776238740",
    "into": "13310.00",
    "inth": "13313.00",
    "intl": "13306.00",
    "intc": "13313.00",
    "intvwap": "13311.15",
    "intv": "622",
    "intoi": "0",
    "v": "465150",
    "oi": "0"
  },
  {
    "stat": "Ok",
    "time": "15-04-2026 13:10:00",
    "ssboe": "1776238800",
    "into": "13312.00",
    "inth": "13314.00",
    "intl": "13309.00",
    "intc": "13312.00",
    "intvwap": "13311.47",
    "intv": "844",
    "intoi": "0",
    "v": "465994",
    "oi": "0"
  },
  {
    "stat": "Ok",
    "time": "15-04-2026 13:11:00",
    "ssboe": "1776238860",
    "into": "13313.00",
    "inth": "13314.00",
    "intl": "13312.00",
    "intc": "13314.00",
    "intvwap": "13314.00",
    "intv": "785",
    "intoi": "0",
    "v": "466779",
    "oi": "0"
  },
  {
    "stat": "Ok",
    "time": "15-04-2026 13:12:00",
    "ssboe": "1776238920",
    "into": "13317.00",
    "inth": "13317.00",
    "intl": "13311.00",
    "intc": "13315.00",
    "intvwap": "13311.30",
    "intv": "843",
    "intoi": "0",
    "v": "467622",
    "oi": "0"
  },
  {
    "stat": "Ok",
    "time": "15-04-2026 13:13:00",
    "ssboe": "1776238980",
    "into": "13313.00",
    "inth": "13317.00",
    "intl": "13313.00",
    "intc": "13315.00",
    "intvwap": "13317.00",
    "intv": "657",
    "intoi": "0",
    "v": "468279",
    "oi": "0"
  },
  {
    "stat": "Ok",
    "time": "15-04-2026 13:14:00",
    "ssboe": "1776239040",
    "into": "13314.00",
    "inth": "13315.00",
    "intl": "13311.00",
    "intc": "13311.00",
    "intvwap": "13311.00",
    "intv": "564",
    "intoi": "0",
    "v": "468843",
    "oi": "0"
  },
  {
    "stat": "Ok",
    "time": "15-04-2026 13:15:00",
    "ssboe": "1776239100",
    "into": "13312.00",
    "inth": "13313.00",
    "intl": "13306.00",
    "intc": "13311.00",
    "intvwap": "13312.95",
    "intv": "459",
    "intoi": "0",
    "v": "469302",
    "oi": "0"
  },
  {
    "stat": "Ok",
    "time": "15-04-2026 13:16:00",
    "ssboe": "1776239160",
    "into": "13310.00",
    "inth": "13314.00",
    "intl": "13305.00",
    "intc": "13314.00",
    "intvwap": "13312.77",
    "intv": "913",
    "intoi": "0",
    "v": "470215",
    "oi": "0"
  },
  {
    "stat": "Ok",
    "time": "15-04-2026 13:17:00",
    "ssboe": "1776239220",
    "into": "13313.00",
    "inth": "13317.00",
    "intl": "13308.00",
    "intc": "13317.00",
    "intvwap": "13312.58",
    "intv": "908",
    "intoi": "0",
    "v": "471123",
    "oi": "0"
  },
  {
    "stat": "Ok",
    "time": "15-04-2026 13:18:00",
    "ssboe": "1776239280",
    "into": "13314.00",
    "inth": "13317.00",
    "intl": "13312.00",
    "intc": "13316.00",
    "intvwap": "13314.05",
    "intv": "490",
    "intoi": "0",
    "v": "471613",
    "oi": "0"
  },
  {
    "stat": "Ok",
    "time": "15-04-2026 13:19:00",
    "ssboe": "1776239340",
    "into": "13317.00",
    "inth": "13317.00",
    "intl": "13312.00",
    "intc": "13315.00",
    "intvwap": "13312.00",
    "intv": "658",
    "intoi": "0",
    "v": "472271",
    "oi": "0"
  },
  {
    "stat": "Ok",
    "time": "15-04-2026 13:20:00",
    "ssboe": "1776239400",
    "into": "13314.00",
    "inth": "13315.00",
    "intl": "13311.00",
    "intc": "13311.00",
    "intvwap": "13311.00",
    "intv": "628",
    "intoi": "0",
    "v": "472899",
    "oi": "0"
  },
  {
    "stat": "Ok",
    "time": "15-04-2026 13:21:00",
    "ssboe": "1776239460",
    "into": "13314.00",
    "inth": "13315.00",
    "intl": "13309.00",
    "intc": "13309.00",
    "intvwap": "13313.87",
    "intv": "980",
    "intoi": "0",
    "v": "473879",
    "oi": "0"
  },
  {
    "stat": "Ok",
    "time": "15-04-2026 13:22:00",
    "ssboe": "1776239520",
    "into": "13308.00",
    "inth": "13308.00",
    "intl": "13301.00",
    "intc": "13301.00",
    "intvwap": "13301.54",
    "intv": "600",
    "intoi": "0",
    "v": "474479",
    "oi": "0"
  },
  {
    "stat": "Ok",
    "time": "15-04-2026 13:23:00",
    "ssboe": "1776239580",
    "into": "13303.00",
    "inth": "13303.00",
    "intl": "13292.00",
    "intc": "13292.00",
    "intvwap": "13300.26",
    "intv": "3636",
    "intoi": "0",
    "v": "478115",
    "oi": "0"
  },
  {
    "stat": "Ok",
    "time": "15-04-2026 13:24:00",
    "ssboe": "1776239640",
    "into": "13290.00",
    "inth": "13292.00",
    "intl": "13279.00",
    "intc": "13283.00",
    "intvwap": "13285.33",
    "intv": "2527",
    "intoi": "0",
    "v": "480642",
    "oi": "0"
  },
  {
    "stat": "Ok",
    "time": "15-04-2026 13:25:00",
    "ssboe": "1776239700",
    "into": "13279.00",
    "inth": "13279.00",
    "intl": "13272.00",
    "intc": "13277.00",
    "intvwap": "13274.47",
    "intv": "1908",
    "intoi": "0",
    "v": "482550",
    "oi": "0"
  },
  {
    "stat": "Ok",
    "time": "15-04-2026 13:26:00",
    "ssboe": "1776239760",
    "into": "13278.00",
    "inth": "13283.00",
    "intl": "13277.00",
    "intc": "13283.00",
    "intvwap": "13280.49",
    "intv": "1118",
    "intoi": "0",
    "v": "483668",
    "oi": "0"
  },
  {
    "stat": "Ok",
    "time": "15-04-2026 13:27:00",
    "ssboe": "1776239820",
    "into": "13281.00",
    "inth": "13287.00",
    "intl": "13280.00",
    "intc": "13280.00",
    "intvwap": "13282.72",
    "intv": "782",
    "intoi": "0",
    "v": "484450",
    "oi": "0"
  },
  {
    "stat": "Ok",
    "time": "15-04-2026 13:28:00",
    "ssboe": "1776239880",
    "into": "13283.00",
    "inth": "13283.00",
    "intl": "13280.00",
    "intc": "13283.00",
    "intvwap": "13282.46",
    "intv": "585",
    "intoi": "0",
    "v": "485035",
    "oi": "0"
  },
  {
    "stat": "Ok",
    "time": "15-04-2026 13:29:00",
    "ssboe": "1776239940",
    "into": "13282.00",
    "inth": "13282.00",
    "intl": "13278.00",
    "intc": "13278.00",
    "intvwap": "13282.00",
    "intv": "901",
    "intoi": "0",
    "v": "485936",
    "oi": "0"
  },
  {
    "stat": "Ok",
    "time": "15-04-2026 13:30:00",
    "ssboe": "1776240000",
    "into": "13280.00",
    "inth": "13297.00",
    "intl": "13280.00",
    "intc": "13297.00",
    "intvwap": "13286.63",
    "intv": "1072",
    "intoi": "0",
    "v": "487008",
    "oi": "0"
  },
  {
    "stat": "Ok",
    "time": "15-04-2026 13:31:00",
    "ssboe": "1776240060",
    "into": "13298.00",
    "inth": "13314.00",
    "intl": "13295.00",
    "intc": "13305.00",
    "intvwap": "13304.11",
    "intv": "1403",
    "intoi": "0",
    "v": "488411",
    "oi": "0"
  },
  {
    "stat": "Ok",
    "time": "15-04-2026 13:32:00",
    "ssboe": "1776240120",
    "into": "13309.00",
    "inth": "13320.00",
    "intl": "13309.00",
    "intc": "13313.00",
    "intvwap": "13315.04",
    "intv": "1163",
    "intoi": "0",
    "v": "489574",
    "oi": "0"
  },
  {
    "stat": "Ok",
    "time": "15-04-2026 13:33:00",
    "ssboe": "1776240180",
    "into": "13312.00",
    "inth": "13313.00",
    "intl": "13300.00",
    "intc": "13303.00",
    "intvwap": "13305.58",
    "intv": "934",
    "intoi": "0",
    "v": "490508",
    "oi": "0"
  },
  {
    "stat": "Ok",
    "time": "15-04-2026 13:34:00",
    "ssboe": "1776240240",
    "into": "13305.00",
    "inth": "13308.00",
    "intl": "13302.00",
    "intc": "13303.00",
    "intvwap": "13302.00",
    "intv": "442",
    "intoi": "0",
    "v": "490950",
    "oi": "0"
  },
  {
    "stat": "Ok",
    "time": "15-04-2026 13:35:00",
    "ssboe": "1776240300",
    "into": "13302.00",
    "inth": "13314.00",
    "intl": "13302.00",
    "intc": "13313.00",
    "intvwap": "13308.63",
    "intv": "1064",
    "intoi": "0",
    "v": "492014",
    "oi": "0"
  },
  {
    "stat": "Ok",
    "time": "15-04-2026 13:36:00",
    "ssboe": "1776240360",
    "into": "13312.00",
    "inth": "13320.00",
    "intl": "13311.00",
    "intc": "13320.00",
    "intvwap": "13318.00",
    "intv": "1079",
    "intoi": "0",
    "v": "493093",
    "oi": "0"
  },
  {
    "stat": "Ok",
    "time": "15-04-2026 13:37:00",
    "ssboe": "1776240420",
    "into": "13318.00",
    "inth": "13321.00",
    "intl": "13313.00",
    "intc": "13314.00",
    "intvwap": "13313.00",
    "intv": "780",
    "intoi": "0",
    "v": "493873",
    "oi": "0"
  },
  {
    "stat": "Ok",
    "time": "15-04-2026 13:38:00",
    "ssboe": "1776240480",
    "into": "13313.00",
    "inth": "13317.00",
    "intl": "13307.00",
    "intc": "13316.00",
    "intvwap": "13315.80",
    "intv": "937",
    "intoi": "0",
    "v": "494810",
    "oi": "0"
  },
  {
    "stat": "Ok",
    "time": "15-04-2026 13:39:00",
    "ssboe": "1776240540",
    "into": "13317.00",
    "inth": "13317.00",
    "intl": "13304.00",
    "intc": "13310.00",
    "intvwap": "13311.53",
    "intv": "740",
    "intoi": "0",
    "v": "495550",
    "oi": "0"
  },
  {
    "stat": "Ok",
    "time": "15-04-2026 13:40:00",
    "ssboe": "1776240600",
    "into": "13309.00",
    "inth": "13320.00",
    "intl": "13309.00",
    "intc": "13319.00",
    "intvwap": "13313.12",
    "intv": "1076",
    "intoi": "0",
    "v": "496626",
    "oi": "0"
  },
  {
    "stat": "Ok",
    "time": "15-04-2026 13:41:00",
    "ssboe": "1776240660",
    "into": "13318.00",
    "inth": "13319.00",
    "intl": "13312.00",
    "intc": "13312.00",
    "intvwap": "13312.64",
    "intv": "526",
    "intoi": "0",
    "v": "497152",
    "oi": "0"
  },
  {
    "stat": "Ok",
    "time": "15-04-2026 13:42:00",
    "ssboe": "1776240720",
    "into": "13315.00",
    "inth": "13319.00",
    "intl": "13315.00",
    "intc": "13319.00",
    "intvwap": "13319.00",
    "intv": "618",
    "intoi": "0",
    "v": "497770",
    "oi": "0"
  },
  {
    "stat": "Ok",
    "time": "15-04-2026 13:43:00",
    "ssboe": "1776240780",
    "into": "13318.00",
    "inth": "13319.00",
    "intl": "13313.00",
    "intc": "13315.00",
    "intvwap": "13313.00",
    "intv": "462",
    "intoi": "0",
    "v": "498232",
    "oi": "0"
  },
  {
    "stat": "Ok",
    "time": "15-04-2026 13:44:00",
    "ssboe": "1776240840",
    "into": "13314.00",
    "inth": "13326.00",
    "intl": "13314.00",
    "intc": "13323.00",
    "intvwap": "13320.12",
    "intv": "1318",
    "intoi": "0",
    "v": "499550",
    "oi": "0"
  },
  {
    "stat": "Ok",
    "time": "15-04-2026 13:45:00",
    "ssboe": "1776240900",
    "into": "13324.00",
    "inth": "13324.00",
    "intl": "13319.00",
    "intc": "13323.00",
    "intvwap": "13321.34",
    "intv": "494",
    "intoi": "0",
    "v": "500044",
    "oi": "0"
  },
  {
    "stat": "Ok",
    "time": "15-04-2026 13:46:00",
    "ssboe": "1776240960",
    "into": "13321.00",
    "inth": "13323.00",
    "intl": "13310.00",
    "intc": "13311.00",
    "intvwap": "13317.27",
    "intv": "1414",
    "intoi": "0",
    "v": "501458",
    "oi": "0"
  },
  {
    "stat": "Ok",
    "time": "15-04-2026 13:47:00",
    "ssboe": "1776241020",
    "into": "13304.00",
    "inth": "13318.00",
    "intl": "13301.00",
    "intc": "13314.00",
    "intvwap": "13304.05",
    "intv": "1102",
    "intoi": "0",
    "v": "502560",
    "oi": "0"
  },
  {
    "stat": "Ok",
    "time": "15-04-2026 13:48:00",
    "ssboe": "1776241080",
    "into": "13307.00",
    "inth": "13315.00",
    "intl": "13305.00",
    "intc": "13310.00",
    "intvwap": "13315.00",
    "intv": "637",
    "intoi": "0",
    "v": "503197",
    "oi": "0"
  },
  {
    "stat": "Ok",
    "time": "15-04-2026 13:49:00",
    "ssboe": "1776241140",
    "into": "13306.00",
    "inth": "13311.00",
    "intl": "13306.00",
    "intc": "13311.00",
    "intvwap": "13306.00",
    "intv": "561",
    "intoi": "0",
    "v": "503758",
    "oi": "0"
  },
  {
    "stat": "Ok",
    "time": "15-04-2026 13:50:00",
    "ssboe": "1776241200",
    "into": "13307.00",
    "inth": "13311.00",
    "intl": "13307.00",
    "intc": "13308.00",
    "intvwap": "13311.00",
    "intv": "415",
    "intoi": "0",
    "v": "504173",
    "oi": "0"
  },
  {
    "stat": "Ok",
    "time": "15-04-2026 13:51:00",
    "ssboe": "1776241260",
    "into": "13309.00",
    "inth": "13311.00",
    "intl": "13306.00",
    "intc": "13311.00",
    "intvwap": "13306.00",
    "intv": "486",
    "intoi": "0",
    "v": "504659",
    "oi": "0"
  },
  {
    "stat": "Ok",
    "time": "15-04-2026 13:52:00",
    "ssboe": "1776241320",
    "into": "13310.00",
    "inth": "13311.00",
    "intl": "13301.00",
    "intc": "13303.00",
    "intvwap": "13306.87",
    "intv": "829",
    "intoi": "0",
    "v": "505488",
    "oi": "0"
  },
  {
    "stat": "Ok",
    "time": "15-04-2026 13:53:00",
    "ssboe": "1776241380",
    "into": "13300.00",
    "inth": "13304.00",
    "intl": "13300.00",
    "intc": "13304.00",
    "intvwap": "13300.35",
    "intv": "1478",
    "intoi": "0",
    "v": "506966",
    "oi": "0"
  },
  {
    "stat": "Ok",
    "time": "15-04-2026 13:54:00",
    "ssboe": "1776241440",
    "into": "13303.00",
    "inth": "13307.00",
    "intl": "13300.00",
    "intc": "13307.00",
    "intvwap": "13304.09",
    "intv": "563",
    "intoi": "0",
    "v": "507529",
    "oi": "0"
  },
  {
    "stat": "Ok",
    "time": "15-04-2026 13:55:00",
    "ssboe": "1776241500",
    "into": "13308.00",
    "inth": "13318.00",
    "intl": "13305.00",
    "intc": "13314.00",
    "intvwap": "13314.60",
    "intv": "924",
    "intoi": "0",
    "v": "508453",
    "oi": "0"
  },
  {
    "stat": "Ok",
    "time": "15-04-2026 13:56:00",
    "ssboe": "1776241560",
    "into": "13315.00",
    "inth": "13320.00",
    "intl": "13313.00",
    "intc": "13320.00",
    "intvwap": "13318.08",
    "intv": "784",
    "intoi": "0",
    "v": "509237",
    "oi": "0"
  },
  {
    "stat": "Ok",
    "time": "15-04-2026 13:57:00",
    "ssboe": "1776241620",
    "into": "13319.00",
    "inth": "13323.00",
    "intl": "13317.00",
    "intc": "13322.00",
    "intvwap": "13317.00",
    "intv": "564",
    "intoi": "0",
    "v": "509801",
    "oi": "0"
  },
  {
    "stat": "Ok",
    "time": "15-04-2026 13:58:00",
    "ssboe": "1776241680",
    "into": "13321.00",
    "inth": "13323.00",
    "intl": "13317.00",
    "intc": "13319.00",
    "intvwap": "13323.00",
    "intv": "671",
    "intoi": "0",
    "v": "510472",
    "oi": "0"
  },
  {
    "stat": "Ok",
    "time": "15-04-2026 13:59:00",
    "ssboe": "1776241740",
    "into": "13316.00",
    "inth": "13320.00",
    "intl": "13315.00",
    "intc": "13320.00",
    "intvwap": "13320.00",
    "intv": "607",
    "intoi": "0",
    "v": "511079",
    "oi": "0"
  },
  {
    "stat": "Ok",
    "time": "15-04-2026 14:00:00",
    "ssboe": "1776241800",
    "into": "13321.00",
    "inth": "13322.00",
    "intl": "13316.00",
    "intc": "13319.00",
    "intvwap": "13317.72",
    "intv": "770",
    "intoi": "0",
    "v": "511849",
    "oi": "0"
  },
  {
    "stat": "Ok",
    "time": "15-04-2026 14:01:00",
    "ssboe": "1776241860",
    "into": "13317.00",
    "inth": "13317.00",
    "intl": "13312.00",
    "intc": "13315.00",
    "intvwap": "13313.42",
    "intv": "583",
    "intoi": "0",
    "v": "512432",
    "oi": "0"
  },
  {
    "stat": "Ok",
    "time": "15-04-2026 14:02:00",
    "ssboe": "1776241920",
    "into": "13314.00",
    "inth": "13328.00",
    "intl": "13313.00",
    "intc": "13321.00",
    "intvwap": "13320.63",
    "intv": "1491",
    "intoi": "0",
    "v": "513923",
    "oi": "0"
  },
  {
    "stat": "Ok",
    "time": "15-04-2026 14:03:00",
    "ssboe": "1776241980",
    "into": "13319.00",
    "inth": "13320.00",
    "intl": "13317.00",
    "intc": "13319.00",
    "intvwap": "13318.37",
    "intv": "409",
    "intoi": "0",
    "v": "514332",
    "oi": "0"
  },
  {
    "stat": "Ok",
    "time": "15-04-2026 14:04:00",
    "ssboe": "1776242040",
    "into": "13316.00",
    "inth": "13320.00",
    "intl": "13313.00",
    "intc": "13315.00",
    "intvwap": "13320.00",
    "intv": "670",
    "intoi": "0",
    "v": "515002",
    "oi": "0"
  },
  {
    "stat": "Ok",
    "time": "15-04-2026 14:05:00",
    "ssboe": "1776242100",
    "into": "13313.00",
    "inth": "13316.00",
    "intl": "13305.00",
    "intc": "13305.00",
    "intvwap": "13306.42",
    "intv": "842",
    "intoi": "0",
    "v": "515844",
    "oi": "0"
  },
  {
    "stat": "Ok",
    "time": "15-04-2026 14:06:00",
    "ssboe": "1776242160",
    "into": "13306.00",
    "inth": "13308.00",
    "intl": "13295.00",
    "intc": "13295.00",
    "intvwap": "13302.64",
    "intv": "1465",
    "intoi": "0",
    "v": "517309",
    "oi": "0"
  },
  {
    "stat": "Ok",
    "time": "15-04-2026 14:07:00",
    "ssboe": "1776242220",
    "into": "13292.00",
    "inth": "13295.00",
    "intl": "13290.00",
    "intc": "13294.00",
    "intvwap": "13295.00",
    "intv": "1016",
    "intoi": "0",
    "v": "518325",
    "oi": "0"
  },
  {
    "stat": "Ok",
    "time": "15-04-2026 14:08:00",
    "ssboe": "1776242280",
    "into": "13295.00",
    "inth": "13297.00",
    "intl": "13291.00",
    "intc": "13296.00",
    "intvwap": "13295.57",
    "intv": "886",
    "intoi": "0",
    "v": "519211",
    "oi": "0"
  },
  {
    "stat": "Ok",
    "time": "15-04-2026 14:09:00",
    "ssboe": "1776242340",
    "into": "13295.00",
    "inth": "13295.00",
    "intl": "13287.00",
    "intc": "13287.00",
    "intvwap": "13289.41",
    "intv": "2021",
    "intoi": "0",
    "v": "521232",
    "oi": "0"
  },
  {
    "stat": "Ok",
    "time": "15-04-2026 14:10:00",
    "ssboe": "1776242400",
    "into": "13289.00",
    "inth": "13289.00",
    "intl": "13275.00",
    "intc": "13282.00",
    "intvwap": "13278.84",
    "intv": "2025",
    "intoi": "0",
    "v": "523257",
    "oi": "0"
  },
  {
    "stat": "Ok",
    "time": "15-04-2026 14:11:00",
    "ssboe": "1776242460",
    "into": "13283.00",
    "inth": "13293.00",
    "intl": "13280.00",
    "intc": "13288.00",
    "intvwap": "13286.63",
    "intv": "960",
    "intoi": "0",
    "v": "524217",
    "oi": "0"
  },
  {
    "stat": "Ok",
    "time": "15-04-2026 14:12:00",
    "ssboe": "1776242520",
    "into": "13296.00",
    "inth": "13296.00",
    "intl": "13290.00",
    "intc": "13295.00",
    "intvwap": "13295.32",
    "intv": "1204",
    "intoi": "0",
    "v": "525421",
    "oi": "0"
  },
  {
    "stat": "Ok",
    "time": "15-04-2026 14:13:00",
    "ssboe": "1776242580",
    "into": "13296.00",
    "inth": "13296.00",
    "intl": "13285.00",
    "intc": "13285.00",
    "intvwap": "13286.63",
    "intv": "1210",
    "intoi": "0",
    "v": "526631",
    "oi": "0"
  },
  {
    "stat": "Ok",
    "time": "15-04-2026 14:14:00",
    "ssboe": "1776242640",
    "into": "13283.00",
    "inth": "13283.00",
    "intl": "13277.00",
    "intc": "13279.00",
    "intvwap": "13281.96",
    "intv": "2420",
    "intoi": "0",
    "v": "529051",
    "oi": "0"
  },
  {
    "stat": "Ok",
    "time": "15-04-2026 14:15:00",
    "ssboe": "1776242700",
    "into": "13278.00",
    "inth": "13280.00",
    "intl": "13276.00",
    "intc": "13276.00",
    "intvwap": "13276.00",
    "intv": "673",
    "intoi": "0",
    "v": "529724",
    "oi": "0"
  },
  {
    "stat": "Ok",
    "time": "15-04-2026 14:16:00",
    "ssboe": "1776242760",
    "into": "13279.00",
    "inth": "13288.00",
    "intl": "13276.00",
    "intc": "13283.00",
    "intvwap": "13282.82",
    "intv": "3064",
    "intoi": "0",
    "v": "532788",
    "oi": "0"
  },
  {
    "stat": "Ok",
    "time": "15-04-2026 14:17:00",
    "ssboe": "1776242820",
    "into": "13282.00",
    "inth": "13283.00",
    "intl": "13279.00",
    "intc": "13280.00",
    "intvwap": "13279.89",
    "intv": "2157",
    "intoi": "0",
    "v": "534945",
    "oi": "0"
  },
  {
    "stat": "Ok",
    "time": "15-04-2026 14:18:00",
    "ssboe": "1776242880",
    "into": "13282.00",
    "inth": "13282.00",
    "intl": "13279.00",
    "intc": "13282.00",
    "intvwap": "13279.00",
    "intv": "740",
    "intoi": "0",
    "v": "535685",
    "oi": "0"
  },
  {
    "stat": "Ok",
    "time": "15-04-2026 14:19:00",
    "ssboe": "1776242940",
    "into": "13280.00",
    "inth": "13282.00",
    "intl": "13278.00",
    "intc": "13282.00",
    "intvwap": "13280.86",
    "intv": "2001",
    "intoi": "0",
    "v": "537686",
    "oi": "0"
  },
  {
    "stat": "Ok",
    "time": "15-04-2026 14:20:00",
    "ssboe": "1776243000",
    "into": "13285.00",
    "inth": "13288.00",
    "intl": "13282.00",
    "intc": "13288.00",
    "intvwap": "13284.45",
    "intv": "2544",
    "intoi": "0",
    "v": "540230",
    "oi": "0"
  },
  {
    "stat": "Ok",
    "time": "15-04-2026 14:21:00",
    "ssboe": "1776243060",
    "into": "13287.00",
    "inth": "13288.00",
    "intl": "13285.00",
    "intc": "13286.00",
    "intvwap": "13286.18",
    "intv": "888",
    "intoi": "0",
    "v": "541118",
    "oi": "0"
  },
  {
    "stat": "Ok",
    "time": "15-04-2026 14:22:00",
    "ssboe": "1776243120",
    "into": "13287.00",
    "inth": "13289.00",
    "intl": "13286.00",
    "intc": "13286.00",
    "intvwap": "13286.87",
    "intv": "1165",
    "intoi": "0",
    "v": "542283",
    "oi": "0"
  },
  {
    "stat": "Ok",
    "time": "15-04-2026 14:23:00",
    "ssboe": "1776243180",
    "into": "13285.00",
    "inth": "13287.00",
    "intl": "13282.00",
    "intc": "13285.00",
    "intvwap": "13285.41",
    "intv": "753",
    "intoi": "0",
    "v": "543036",
    "oi": "0"
  },
  {
    "stat": "Ok",
    "time": "15-04-2026 14:24:00",
    "ssboe": "1776243240",
    "into": "13284.00",
    "inth": "13285.00",
    "intl": "13281.00",
    "intc": "13282.00",
    "intvwap": "13282.43",
    "intv": "1533",
    "intoi": "0",
    "v": "544569",
    "oi": "0"
  },
  {
    "stat": "Ok",
    "time": "15-04-2026 14:25:00",
    "ssboe": "1776243300",
    "into": "13281.00",
    "inth": "13286.00",
    "intl": "13281.00",
    "intc": "13286.00",
    "intvwap": "13284.60",
    "intv": "870",
    "intoi": "0",
    "v": "545439",
    "oi": "0"
  },
  {
    "stat": "Ok",
    "time": "15-04-2026 14:26:00",
    "ssboe": "1776243360",
    "into": "13285.00",
    "inth": "13286.00",
    "intl": "13283.00",
    "intc": "13283.00",
    "intvwap": "13283.00",
    "intv": "842",
    "intoi": "0",
    "v": "546281",
    "oi": "0"
  },
  {
    "stat": "Ok",
    "time": "15-04-2026 14:27:00",
    "ssboe": "1776243420",
    "into": "13285.00",
    "inth": "13285.00",
    "intl": "13276.00",
    "intc": "13279.00",
    "intvwap": "13282.26",
    "intv": "1784",
    "intoi": "0",
    "v": "548065",
    "oi": "0"
  },
  {
    "stat": "Ok",
    "time": "15-04-2026 14:28:00",
    "ssboe": "1776243480",
    "into": "13280.00",
    "inth": "13280.00",
    "intl": "13275.00",
    "intc": "13276.00",
    "intvwap": "13277.43",
    "intv": "865",
    "intoi": "0",
    "v": "548930",
    "oi": "0"
  },
  {
    "stat": "Ok",
    "time": "15-04-2026 14:29:00",
    "ssboe": "1776243540",
    "into": "13275.00",
    "inth": "13295.00",
    "intl": "13275.00",
    "intc": "13295.00",
    "intvwap": "13279.95",
    "intv": "4365",
    "intoi": "0",
    "v": "553295",
    "oi": "0"
  },
  {
    "stat": "Ok",
    "time": "15-04-2026 14:30:00",
    "ssboe": "1776243600",
    "into": "13293.00",
    "inth": "13297.00",
    "intl": "13291.00",
    "intc": "13291.00",
    "intvwap": "13291.00",
    "intv": "2274",
    "intoi": "0",
    "v": "555569",
    "oi": "0"
  },
  {
    "stat": "Ok",
    "time": "15-04-2026 14:31:00",
    "ssboe": "1776243660",
    "into": "13294.00",
    "inth": "13297.00",
    "intl": "13290.00",
    "intc": "13296.00",
    "intvwap": "13295.78",
    "intv": "1226",
    "intoi": "0",
    "v": "556795",
    "oi": "0"
  },
  {
    "stat": "Ok",
    "time": "15-04-2026 14:32:00",
    "ssboe": "1776243720",
    "into": "13295.00",
    "inth": "13305.00",
    "intl": "13291.00",
    "intc": "13305.00",
    "intvwap": "13297.82",
    "intv": "3207",
    "intoi": "0",
    "v": "560002",
    "oi": "0"
  },
  {
    "stat": "Ok",
    "time": "15-04-2026 14:33:00",
    "ssboe": "1776243780",
    "into": "13304.00",
    "inth": "13304.00",
    "intl": "13300.00",
    "intc": "13300.00",
    "intvwap": "13301.67",
    "intv": "874",
    "intoi": "0",
    "v": "560876",
    "oi": "0"
  },
  {
    "stat": "Ok",
    "time": "15-04-2026 14:34:00",
    "ssboe": "1776243840",
    "into": "13301.00",
    "inth": "13315.00",
    "intl": "13300.00",
    "intc": "13312.00",
    "intvwap": "13306.54",
    "intv": "1626",
    "intoi": "0",
    "v": "562502",
    "oi": "0"
  },
  {
    "stat": "Ok",
    "time": "15-04-2026 14:35:00",
    "ssboe": "1776243900",
    "into": "13308.00",
    "inth": "13309.00",
    "intl": "13302.00",
    "intc": "13308.00",
    "intvwap": "13309.00",
    "intv": "1317",
    "intoi": "0",
    "v": "563819",
    "oi": "0"
  },
  {
    "stat": "Ok",
    "time": "15-04-2026 14:36:00",
    "ssboe": "1776243960",
    "into": "13309.00",
    "inth": "13311.00",
    "intl": "13304.00",
    "intc": "13304.00",
    "intvwap": "13306.29",
    "intv": "1081",
    "intoi": "0",
    "v": "564900",
    "oi": "0"
  },
  {
    "stat": "Ok",
    "time": "15-04-2026 14:37:00",
    "ssboe": "1776244020",
    "into": "13307.00",
    "inth": "13307.00",
    "intl": "13287.00",
    "intc": "13287.00",
    "intvwap": "13298.75",
    "intv": "3401",
    "intoi": "0",
    "v": "568301",
    "oi": "0"
  },
  {
    "stat": "Ok",
    "time": "15-04-2026 14:38:00",
    "ssboe": "1776244080",
    "into": "13288.00",
    "inth": "13291.00",
    "intl": "13283.00",
    "intc": "13283.00",
    "intvwap": "13289.35",
    "intv": "756",
    "intoi": "0",
    "v": "569057",
    "oi": "0"
  },
  {
    "stat": "Ok",
    "time": "15-04-2026 14:39:00",
    "ssboe": "1776244140",
    "into": "13286.00",
    "inth": "13295.00",
    "intl": "13282.00",
    "intc": "13292.00",
    "intvwap": "13286.93",
    "intv": "1569",
    "intoi": "0",
    "v": "570626",
    "oi": "0"
  },
  {
    "stat": "Ok",
    "time": "15-04-2026 14:40:00",
    "ssboe": "1776244200",
    "into": "13294.00",
    "inth": "13295.00",
    "intl": "13290.00",
    "intc": "13293.00",
    "intvwap": "13295.00",
    "intv": "806",
    "intoi": "0",
    "v": "571432",
    "oi": "0"
  },
  {
    "stat": "Ok",
    "time": "15-04-2026 14:41:00",
    "ssboe": "1776244260",
    "into": "13292.00",
    "inth": "13293.00",
    "intl": "13282.00",
    "intc": "13286.00",
    "intvwap": "13283.41",
    "intv": "1056",
    "intoi": "0",
    "v": "572488",
    "oi": "0"
  },
  {
    "stat": "Ok",
    "time": "15-04-2026 14:42:00",
    "ssboe": "1776244320",
    "into": "13284.00",
    "inth": "13289.00",
    "intl": "13280.00",
    "intc": "13285.00",
    "intvwap": "13283.75",
    "intv": "1738",
    "intoi": "0",
    "v": "574226",
    "oi": "0"
  },
  {
    "stat": "Ok",
    "time": "15-04-2026 14:43:00",
    "ssboe": "1776244380",
    "into": "13286.00",
    "inth": "13289.00",
    "intl": "13283.00",
    "intc": "13286.00",
    "intvwap": "13289.00",
    "intv": "573",
    "intoi": "0",
    "v": "574799",
    "oi": "0"
  },
  {
    "stat": "Ok",
    "time": "15-04-2026 14:44:00",
    "ssboe": "1776244440",
    "into": "13287.00",
    "inth": "13288.00",
    "intl": "13282.00",
    "intc": "13284.00",
    "intvwap": "13284.53",
    "intv": "1509",
    "intoi": "0",
    "v": "576308",
    "oi": "0"
  },
  {
    "stat": "Ok",
    "time": "15-04-2026 14:45:00",
    "ssboe": "1776244500",
    "into": "13282.00",
    "inth": "13297.00",
    "intl": "13282.00",
    "intc": "13296.00",
    "intvwap": "13288.25",
    "intv": "1817",
    "intoi": "0",
    "v": "578125",
    "oi": "0"
  },
  {
    "stat": "Ok",
    "time": "15-04-2026 14:46:00",
    "ssboe": "1776244560",
    "into": "13295.00",
    "inth": "13302.00",
    "intl": "13294.00",
    "intc": "13302.00",
    "intvwap": "13299.81",
    "intv": "3070",
    "intoi": "0",
    "v": "581195",
    "oi": "0"
  },
  {
    "stat": "Ok",
    "time": "15-04-2026 14:47:00",
    "ssboe": "1776244620",
    "into": "13301.00",
    "inth": "13302.00",
    "intl": "13300.00",
    "intc": "13300.00",
    "intvwap": "13302.00",
    "intv": "603",
    "intoi": "0",
    "v": "581798",
    "oi": "0"
  },
  {
    "stat": "Ok",
    "time": "15-04-2026 14:48:00",
    "ssboe": "1776244680",
    "into": "13302.00",
    "inth": "13302.00",
    "intl": "13300.00",
    "intc": "13300.00",
    "intvwap": "13300.00",
    "intv": "835",
    "intoi": "0",
    "v": "582633",
    "oi": "0"
  }
]